{
"meta":{"test_sets":[],"test_metrics":[],"learn_metrics":[{"best_value":"Min","name":"RMSE"}],"launch_mode":"Train","parameters":"","iteration_count":1000,"learn_sets":["learn"],"name":"experiment"},
"iterations":[
{"learn":[3.772320413],"iteration":0,"passed_time":0.04895041652,"remaining_time":48.9014661},
{"learn":[3.719257043],"iteration":1,"passed_time":0.05006581613,"remaining_time":24.98284225},
{"learn":[3.655984409],"iteration":2,"passed_time":0.05127987972,"remaining_time":17.04201336},
{"learn":[3.596582601],"iteration":3,"passed_time":0.05267575837,"remaining_time":13.11626383},
{"learn":[3.537891231],"iteration":4,"passed_time":0.05388484821,"remaining_time":10.72308479},
{"learn":[3.482674421],"iteration":5,"passed_time":0.05524328398,"remaining_time":9.151970712},
{"learn":[3.426989336],"iteration":6,"passed_time":0.05667734602,"remaining_time":8.040086371},
{"learn":[3.375491157],"iteration":7,"passed_time":0.05925203588,"remaining_time":7.34725245},
{"learn":[3.319604318],"iteration":8,"passed_time":0.06134602273,"remaining_time":6.754878725},
{"learn":[3.278605678],"iteration":9,"passed_time":0.06310666421,"remaining_time":6.247559757},
{"learn":[3.228052208],"iteration":10,"passed_time":0.06488366747,"remaining_time":5.833631557},
{"learn":[3.180874776],"iteration":11,"passed_time":0.0664516092,"remaining_time":5.471182491},
{"learn":[3.137461476],"iteration":12,"passed_time":0.06754515219,"remaining_time":5.128235785},
{"learn":[3.095711362],"iteration":13,"passed_time":0.06867306924,"remaining_time":4.836546162},
{"learn":[3.05392412],"iteration":14,"passed_time":0.06987756476,"remaining_time":4.588626753},
{"learn":[3.010829714],"iteration":15,"passed_time":0.07239023631,"remaining_time":4.451999533},
{"learn":[2.964416111],"iteration":16,"passed_time":0.07363170249,"remaining_time":4.257644915},
{"learn":[2.924816081],"iteration":17,"passed_time":0.07517408825,"remaining_time":4.101164148},
{"learn":[2.88588],"iteration":18,"passed_time":0.07592304396,"remaining_time":3.920026638},
{"learn":[2.847048565],"iteration":19,"passed_time":0.07681645296,"remaining_time":3.764006195},
{"learn":[2.813394811],"iteration":20,"passed_time":0.07771119914,"remaining_time":3.622822093},
{"learn":[2.780367769],"iteration":21,"passed_time":0.07841641104,"remaining_time":3.485965909},
{"learn":[2.744292987],"iteration":22,"passed_time":0.07939301388,"remaining_time":3.372477155},
{"learn":[2.707810285],"iteration":23,"passed_time":0.08046402415,"remaining_time":3.272203649},
{"learn":[2.673237641],"iteration":24,"passed_time":0.08133123775,"remaining_time":3.171918272},
{"learn":[2.644631698],"iteration":25,"passed_time":0.08222411176,"remaining_time":3.080241725},
{"learn":[2.6163486],"iteration":26,"passed_time":0.08313411141,"remaining_time":2.995907052},
{"learn":[2.577662822],"iteration":27,"passed_time":0.08451584988,"remaining_time":2.93390736},
{"learn":[2.547244818],"iteration":28,"passed_time":0.08599300464,"remaining_time":2.879283017},
{"learn":[2.518263303],"iteration":29,"passed_time":0.08705638012,"remaining_time":2.814822957},
{"learn":[2.486171494],"iteration":30,"passed_time":0.08786987907,"remaining_time":2.746642349},
{"learn":[2.459459542],"iteration":31,"passed_time":0.08882142648,"remaining_time":2.686848151},
{"learn":[2.433781992],"iteration":32,"passed_time":0.08987002847,"remaining_time":2.633464168},
{"learn":[2.406763829],"iteration":33,"passed_time":0.09095221954,"remaining_time":2.584113061},
{"learn":[2.386126506],"iteration":34,"passed_time":0.09173154609,"remaining_time":2.529169771},
{"learn":[2.358370345],"iteration":35,"passed_time":0.09308660918,"remaining_time":2.492652535},
{"learn":[2.333926187],"iteration":36,"passed_time":0.09397080343,"remaining_time":2.44578064},
{"learn":[2.307980872],"iteration":37,"passed_time":0.09491290943,"remaining_time":2.402795233},
{"learn":[2.288144768],"iteration":38,"passed_time":0.09582282131,"remaining_time":2.361172597},
{"learn":[2.266724626],"iteration":39,"passed_time":0.09677941803,"remaining_time":2.322706033},
{"learn":[2.242778928],"iteration":40,"passed_time":0.09771436533,"remaining_time":2.285562838},
{"learn":[2.221246631],"iteration":41,"passed_time":0.09954847148,"remaining_time":2.27065323},
{"learn":[2.198908193],"iteration":42,"passed_time":0.1010069145,"remaining_time":2.247991098},
{"learn":[2.179509799],"iteration":43,"passed_time":0.1020287967,"remaining_time":2.216807492},
{"learn":[2.16427727],"iteration":44,"passed_time":0.1027277432,"remaining_time":2.180110995},
{"learn":[2.147766186],"iteration":45,"passed_time":0.1037280326,"remaining_time":2.151229198},
{"learn":[2.125934781],"iteration":46,"passed_time":0.1044840076,"remaining_time":2.118579984},
{"learn":[2.10823409],"iteration":47,"passed_time":0.1055033798,"remaining_time":2.0924837},
{"learn":[2.092732464],"iteration":48,"passed_time":0.1065065575,"remaining_time":2.067096657},
{"learn":[2.075173122],"iteration":49,"passed_time":0.1072098739,"remaining_time":2.036987604},
{"learn":[2.057004407],"iteration":50,"passed_time":0.1081192252,"remaining_time":2.011865583},
{"learn":[2.040308904],"iteration":51,"passed_time":0.1094177865,"remaining_time":1.994770416},
{"learn":[2.019836768],"iteration":52,"passed_time":0.1101750342,"remaining_time":1.968599196},
{"learn":[2.005067057],"iteration":53,"passed_time":0.1109548963,"remaining_time":1.943765406},
{"learn":[1.991131081],"iteration":54,"passed_time":0.1118048732,"remaining_time":1.921011002},
{"learn":[1.974438501],"iteration":55,"passed_time":0.1137548584,"remaining_time":1.917581898},
{"learn":[1.964609293],"iteration":56,"passed_time":0.1155130244,"remaining_time":1.911031263},
{"learn":[1.949475611],"iteration":57,"passed_time":0.1164877261,"remaining_time":1.891921345},
{"learn":[1.938646101],"iteration":58,"passed_time":0.1173147114,"remaining_time":1.871070227},
{"learn":[1.924581743],"iteration":59,"passed_time":0.1181658893,"remaining_time":1.851265599},
{"learn":[1.912824102],"iteration":60,"passed_time":0.1189717685,"remaining_time":1.831385092},
{"learn":[1.900499439],"iteration":61,"passed_time":0.1197271484,"remaining_time":1.811355891},
{"learn":[1.887471962],"iteration":62,"passed_time":0.1205181047,"remaining_time":1.792467684},
{"learn":[1.872330748],"iteration":63,"passed_time":0.1213440438,"remaining_time":1.774656641},
{"learn":[1.857553606],"iteration":64,"passed_time":0.1222475009,"remaining_time":1.758483282},
{"learn":[1.847375335],"iteration":65,"passed_time":0.1234376107,"remaining_time":1.746829218},
{"learn":[1.835501553],"iteration":66,"passed_time":0.1243089036,"remaining_time":1.731047867},
{"learn":[1.817058861],"iteration":67,"passed_time":0.1252297041,"remaining_time":1.716383592},
{"learn":[1.803668798],"iteration":68,"passed_time":0.1262311352,"remaining_time":1.703205606},
{"learn":[1.792797852],"iteration":69,"passed_time":0.1273039993,"remaining_time":1.691324562},
{"learn":[1.782686988],"iteration":70,"passed_time":0.1287565186,"remaining_time":1.684715574},
{"learn":[1.774367267],"iteration":71,"passed_time":0.1299315532,"remaining_time":1.674673353},
{"learn":[1.765001065],"iteration":72,"passed_time":0.131128779,"remaining_time":1.665155864},
{"learn":[1.757039826],"iteration":73,"passed_time":0.1319230295,"remaining_time":1.650820613},
{"learn":[1.748940822],"iteration":74,"passed_time":0.1327237016,"remaining_time":1.636925653},
{"learn":[1.737909345],"iteration":75,"passed_time":0.1334079791,"remaining_time":1.621960167},
{"learn":[1.727671154],"iteration":76,"passed_time":0.1341161615,"remaining_time":1.607652169},
{"learn":[1.717834712],"iteration":77,"passed_time":0.1360808841,"remaining_time":1.608545835},
{"learn":[1.705586382],"iteration":78,"passed_time":0.1375353522,"remaining_time":1.603418473},
{"learn":[1.694650455],"iteration":79,"passed_time":0.1383470284,"remaining_time":1.590990827},
{"learn":[1.6817747],"iteration":80,"passed_time":0.1391635268,"remaining_time":1.578904705},
{"learn":[1.671703439],"iteration":81,"passed_time":0.1402901233,"remaining_time":1.570565039},
{"learn":[1.662741138],"iteration":82,"passed_time":0.1418248415,"remaining_time":1.566908188},
{"learn":[1.657596631],"iteration":83,"passed_time":0.1435948866,"remaining_time":1.565868049},
{"learn":[1.648721187],"iteration":84,"passed_time":0.1451829211,"remaining_time":1.562851445},
{"learn":[1.64235154],"iteration":85,"passed_time":0.1463430362,"remaining_time":1.555320175},
{"learn":[1.63222921],"iteration":86,"passed_time":0.1474212062,"remaining_time":1.547075417},
{"learn":[1.625038305],"iteration":87,"passed_time":0.1485273506,"remaining_time":1.539283451},
{"learn":[1.617897329],"iteration":88,"passed_time":0.1493109709,"remaining_time":1.528340387},
{"learn":[1.611283193],"iteration":89,"passed_time":0.1506245251,"remaining_time":1.522981309},
{"learn":[1.604536469],"iteration":90,"passed_time":0.1513497203,"remaining_time":1.51183402},
{"learn":[1.597175031],"iteration":91,"passed_time":0.1525036311,"remaining_time":1.505144533},
{"learn":[1.590149282],"iteration":92,"passed_time":0.1533417944,"remaining_time":1.495494705},
{"learn":[1.581608723],"iteration":93,"passed_time":0.1544050065,"remaining_time":1.488201446},
{"learn":[1.572155541],"iteration":94,"passed_time":0.1554619855,"remaining_time":1.480979967},
{"learn":[1.564343618],"iteration":95,"passed_time":0.1573046353,"remaining_time":1.481285316},
{"learn":[1.553332142],"iteration":96,"passed_time":0.1583773422,"remaining_time":1.474378763},
{"learn":[1.544477772],"iteration":97,"passed_time":0.1594703597,"remaining_time":1.467778208},
{"learn":[1.539453981],"iteration":98,"passed_time":0.1602586082,"remaining_time":1.458515212},
{"learn":[1.532808064],"iteration":99,"passed_time":0.1613337389,"remaining_time":1.45200365},
{"learn":[1.524476174],"iteration":100,"passed_time":0.1622384159,"remaining_time":1.444082534},
{"learn":[1.519800585],"iteration":101,"passed_time":0.1629641339,"remaining_time":1.434723454},
{"learn":[1.511231534],"iteration":102,"passed_time":0.1638035716,"remaining_time":1.426522367},
{"learn":[1.503089264],"iteration":103,"passed_time":0.1644603354,"remaining_time":1.416889043},
{"learn":[1.497967091],"iteration":104,"passed_time":0.1654650269,"remaining_time":1.410392372},
{"learn":[1.494149274],"iteration":105,"passed_time":0.1664103017,"remaining_time":1.403498205},
{"learn":[1.484384832],"iteration":106,"passed_time":0.1681058333,"remaining_time":1.402976721},
{"learn":[1.47493611],"iteration":107,"passed_time":0.1689791745,"remaining_time":1.395642812},
{"learn":[1.470524552],"iteration":108,"passed_time":0.1699897026,"remaining_time":1.389548853},
{"learn":[1.464170273],"iteration":109,"passed_time":0.171360368,"remaining_time":1.386461159},
{"learn":[1.460501304],"iteration":110,"passed_time":0.1726477101,"remaining_time":1.382737066},
{"learn":[1.455577085],"iteration":111,"passed_time":0.1737023586,"remaining_time":1.377211558},
{"learn":[1.450670237],"iteration":112,"passed_time":0.174727914,"remaining_time":1.371536812},
{"learn":[1.44567213],"iteration":113,"passed_time":0.1757050113,"remaining_time":1.365567018},
{"learn":[1.441523663],"iteration":114,"passed_time":0.1765549443,"remaining_time":1.358705441},
{"learn":[1.43698589],"iteration":115,"passed_time":0.1772562285,"remaining_time":1.350814707},
{"learn":[1.431389705],"iteration":116,"passed_time":0.1780379561,"remaining_time":1.343653976},
{"learn":[1.427366508],"iteration":117,"passed_time":0.1786712599,"remaining_time":1.33549196},
{"learn":[1.418448033],"iteration":118,"passed_time":0.1795535037,"remaining_time":1.329299468},
{"learn":[1.415837192],"iteration":119,"passed_time":0.1814910392,"remaining_time":1.330934288},
{"learn":[1.412132512],"iteration":120,"passed_time":0.1824076598,"remaining_time":1.325093661},
{"learn":[1.40777677],"iteration":121,"passed_time":0.183456584,"remaining_time":1.320285908},
{"learn":[1.407344915],"iteration":122,"passed_time":0.1836469,"remaining_time":1.309417327},
{"learn":[1.404382266],"iteration":123,"passed_time":0.1852769156,"remaining_time":1.308891758},
{"learn":[1.400153083],"iteration":124,"passed_time":0.1865629233,"remaining_time":1.305940463},
{"learn":[1.395839874],"iteration":125,"passed_time":0.187563931,"remaining_time":1.301038696},
{"learn":[1.391555172],"iteration":126,"passed_time":0.1883364794,"remaining_time":1.294627926},
{"learn":[1.385007695],"iteration":127,"passed_time":0.1890998642,"remaining_time":1.288242825},
{"learn":[1.380588897],"iteration":128,"passed_time":0.1898839362,"remaining_time":1.282084561},
{"learn":[1.373159137],"iteration":129,"passed_time":0.1907690098,"remaining_time":1.276684912},
{"learn":[1.368491692],"iteration":130,"passed_time":0.1915026782,"remaining_time":1.270349827},
{"learn":[1.362400415],"iteration":131,"passed_time":0.1924197276,"remaining_time":1.265305482},
{"learn":[1.35859756],"iteration":132,"passed_time":0.1934913751,"remaining_time":1.261330994},
{"learn":[1.354395936],"iteration":133,"passed_time":0.1948688987,"remaining_time":1.259376614},
{"learn":[1.3521881],"iteration":134,"passed_time":0.1957801961,"remaining_time":1.254443479},
{"learn":[1.35002054],"iteration":135,"passed_time":0.1973256318,"remaining_time":1.253598131},
{"learn":[1.345908707],"iteration":136,"passed_time":0.1981546114,"remaining_time":1.248229413},
{"learn":[1.341826698],"iteration":137,"passed_time":0.1991563475,"remaining_time":1.244005591},
{"learn":[1.33778764],"iteration":138,"passed_time":0.2002830184,"remaining_time":1.240602006},
{"learn":[1.334705879],"iteration":139,"passed_time":0.202169727,"remaining_time":1.241899752},
{"learn":[1.328410993],"iteration":140,"passed_time":0.2041293909,"remaining_time":1.243596786},
{"learn":[1.326238144],"iteration":141,"passed_time":0.2051358512,"remaining_time":1.239482819},
{"learn":[1.319693308],"iteration":142,"passed_time":0.2062959224,"remaining_time":1.236332906},
{"learn":[1.318970297],"iteration":143,"passed_time":0.2067442235,"remaining_time":1.228979551},
{"learn":[1.315326555],"iteration":144,"passed_time":0.207641153,"remaining_time":1.224366799},
{"learn":[1.312222103],"iteration":145,"passed_time":0.2085402196,"remaining_time":1.219817449},
{"learn":[1.309516518],"iteration":146,"passed_time":0.2100690585,"remaining_time":1.218972156},
{"learn":[1.3073587],"iteration":147,"passed_time":0.2119664068,"remaining_time":1.220239045},
{"learn":[1.304959481],"iteration":148,"passed_time":0.2134904475,"remaining_time":1.219331348},
{"learn":[1.303183778],"iteration":149,"passed_time":0.2144277226,"remaining_time":1.215090428},
{"learn":[1.299812504],"iteration":150,"passed_time":0.2151929223,"remaining_time":1.209925768},
{"learn":[1.296087468],"iteration":151,"passed_time":0.2159950615,"remaining_time":1.20502508},
{"learn":[1.290218456],"iteration":152,"passed_time":0.216796753,"remaining_time":1.200175489},
{"learn":[1.286974803],"iteration":153,"passed_time":0.2179614613,"remaining_time":1.197372703},
{"learn":[1.282401661],"iteration":154,"passed_time":0.2188223317,"remaining_time":1.192934647},
{"learn":[1.279573578],"iteration":155,"passed_time":0.2196321541,"remaining_time":1.18826627},
{"learn":[1.275797664],"iteration":156,"passed_time":0.220939794,"remaining_time":1.186320041},
{"learn":[1.272595567],"iteration":157,"passed_time":0.2221077667,"remaining_time":1.183637592},
{"learn":[1.27063644],"iteration":158,"passed_time":0.2234445097,"remaining_time":1.181866872},
{"learn":[1.267941114],"iteration":159,"passed_time":0.2246413599,"remaining_time":1.179367139},
{"learn":[1.264251875],"iteration":160,"passed_time":0.2256616215,"remaining_time":1.175963357},
{"learn":[1.263015044],"iteration":161,"passed_time":0.226444788,"remaining_time":1.171362545},
{"learn":[1.261111072],"iteration":162,"passed_time":0.2273481272,"remaining_time":1.16742566},
{"learn":[1.258083213],"iteration":163,"passed_time":0.2281931587,"remaining_time":1.163228541},
{"learn":[1.253511816],"iteration":164,"passed_time":0.2289645499,"remaining_time":1.158699389},
{"learn":[1.251113965],"iteration":165,"passed_time":0.2297132761,"remaining_time":1.15410164},
{"learn":[1.248516555],"iteration":166,"passed_time":0.2304541365,"remaining_time":1.149510753},
{"learn":[1.245813904],"iteration":167,"passed_time":0.2314798136,"remaining_time":1.14637622},
{"learn":[1.243777412],"iteration":168,"passed_time":0.2328141895,"remaining_time":1.144784565},
{"learn":[1.239644594],"iteration":169,"passed_time":0.2336928511,"remaining_time":1.140970979},
{"learn":[1.235233202],"iteration":170,"passed_time":0.2347509317,"remaining_time":1.138061534},
{"learn":[1.233099785],"iteration":171,"passed_time":0.2357932905,"remaining_time":1.135097933},
{"learn":[1.226901957],"iteration":172,"passed_time":0.237108628,"remaining_time":1.133461476},
{"learn":[1.223671098],"iteration":173,"passed_time":0.2384011661,"remaining_time":1.131720478},
{"learn":[1.218510227],"iteration":174,"passed_time":0.2394188684,"remaining_time":1.128688951},
{"learn":[1.215990049],"iteration":175,"passed_time":0.2402780333,"remaining_time":1.124938065},
{"learn":[1.214780559],"iteration":176,"passed_time":0.2411317456,"remaining_time":1.121194501},
{"learn":[1.209985288],"iteration":177,"passed_time":0.241968964,"remaining_time":1.117407238},
{"learn":[1.206957464],"iteration":178,"passed_time":0.2426213256,"remaining_time":1.112805075},
{"learn":[1.204107453],"iteration":179,"passed_time":0.2432859831,"remaining_time":1.108302812},
{"learn":[1.201547377],"iteration":180,"passed_time":0.2440087495,"remaining_time":1.104105889},
{"learn":[1.199536805],"iteration":181,"passed_time":0.2449762631,"remaining_time":1.101047161},
{"learn":[1.192496401],"iteration":182,"passed_time":0.2460245396,"remaining_time":1.098371852},
{"learn":[1.187806346],"iteration":183,"passed_time":0.2468197151,"remaining_time":1.09459178},
{"learn":[1.186250573],"iteration":184,"passed_time":0.2476455293,"remaining_time":1.090978953},
{"learn":[1.184108596],"iteration":185,"passed_time":0.2482174237,"remaining_time":1.086284854},
{"learn":[1.18143717],"iteration":186,"passed_time":0.2489863411,"remaining_time":1.082491419},
{"learn":[1.17874453],"iteration":187,"passed_time":0.2499046383,"remaining_time":1.079375353},
{"learn":[1.177055949],"iteration":188,"passed_time":0.2514082896,"remaining_time":1.078794301},
{"learn":[1.175172602],"iteration":189,"passed_time":0.252967641,"remaining_time":1.078440996},
{"learn":[1.171087872],"iteration":190,"passed_time":0.2542598702,"remaining_time":1.076943639},
{"learn":[1.169064634],"iteration":191,"passed_time":0.2550287837,"remaining_time":1.073246132},
{"learn":[1.167300625],"iteration":192,"passed_time":0.2557887475,"remaining_time":1.06954155},
{"learn":[1.165637826],"iteration":193,"passed_time":0.2565398604,"remaining_time":1.065830554},
{"learn":[1.164428456],"iteration":194,"passed_time":0.257212112,"remaining_time":1.06182436},
{"learn":[1.160932032],"iteration":195,"passed_time":0.2578808394,"remaining_time":1.057837729},
{"learn":[1.156898639],"iteration":196,"passed_time":0.2585996226,"remaining_time":1.054088817},
{"learn":[1.153635557],"iteration":197,"passed_time":0.2595007797,"remaining_time":1.051109219},
{"learn":[1.15201978],"iteration":198,"passed_time":0.2602866177,"remaining_time":1.047686336},
{"learn":[1.147128901],"iteration":199,"passed_time":0.2610247326,"remaining_time":1.04409893},
{"learn":[1.146171221],"iteration":200,"passed_time":0.2620346207,"remaining_time":1.041620209},
{"learn":[1.144822534],"iteration":201,"passed_time":0.2629463653,"remaining_time":1.038768314},
{"learn":[1.141885997],"iteration":202,"passed_time":0.2638635531,"remaining_time":1.035956905},
{"learn":[1.141121021],"iteration":203,"passed_time":0.265751575,"remaining_time":1.036952224},
{"learn":[1.139352578],"iteration":204,"passed_time":0.2667519983,"remaining_time":1.034477262},
{"learn":[1.136809785],"iteration":205,"passed_time":0.2677323127,"remaining_time":1.031939108},
{"learn":[1.133856214],"iteration":206,"passed_time":0.2685311365,"remaining_time":1.028720731},
{"learn":[1.13080676],"iteration":207,"passed_time":0.2692699497,"remaining_time":1.025297116},
{"learn":[1.126391177],"iteration":208,"passed_time":0.2700146544,"remaining_time":1.021921491},
{"learn":[1.124658986],"iteration":209,"passed_time":0.270778933,"remaining_time":1.018644558},
{"learn":[1.123549468],"iteration":210,"passed_time":0.2714736102,"remaining_time":1.015131177},
{"learn":[1.122863567],"iteration":211,"passed_time":0.2722043314,"remaining_time":1.011778364},
{"learn":[1.120280326],"iteration":212,"passed_time":0.2730755138,"remaining_time":1.008969152},
{"learn":[1.118221337],"iteration":213,"passed_time":0.2741415914,"remaining_time":1.006893882},
{"learn":[1.116538002],"iteration":214,"passed_time":0.275066824,"remaining_time":1.004313753},
{"learn":[1.11512873],"iteration":215,"passed_time":0.2759820052,"remaining_time":1.001712463},
{"learn":[1.113668298],"iteration":216,"passed_time":0.2771495439,"remaining_time":1.000037294},
{"learn":[1.11154556],"iteration":217,"passed_time":0.2793904573,"remaining_time":1.002217145},
{"learn":[1.109605621],"iteration":218,"passed_time":0.2806587366,"remaining_time":1.000888006},
{"learn":[1.107774971],"iteration":219,"passed_time":0.2818850949,"remaining_time":0.999410791},
{"learn":[1.105651175],"iteration":220,"passed_time":0.2827607283,"remaining_time":0.9966995807},
{"learn":[1.103946749],"iteration":221,"passed_time":0.2835612148,"remaining_time":0.9937415546},
{"learn":[1.099678601],"iteration":222,"passed_time":0.2843869951,"remaining_time":0.9908910098},
{"learn":[1.0958443],"iteration":223,"passed_time":0.2852887361,"remaining_time":0.9883216928},
{"learn":[1.094798598],"iteration":224,"passed_time":0.2861369663,"remaining_time":0.9855828839},
{"learn":[1.094184439],"iteration":225,"passed_time":0.2870991362,"remaining_time":0.983251024},
{"learn":[1.093389341],"iteration":226,"passed_time":0.288424429,"remaining_time":0.9821677692},
{"learn":[1.091992488],"iteration":227,"passed_time":0.2896849185,"remaining_time":0.9808629698},
{"learn":[1.090638225],"iteration":228,"passed_time":0.2907459785,"remaining_time":0.9788871155},
{"learn":[1.087853908],"iteration":229,"passed_time":0.2918212381,"remaining_time":0.9769667537},
{"learn":[1.085658414],"iteration":230,"passed_time":0.2931280909,"remaining_time":0.9758246834},
{"learn":[1.083439222],"iteration":231,"passed_time":0.2944270171,"remaining_time":0.9746549533},
{"learn":[1.08136974],"iteration":232,"passed_time":0.2954335619,"remaining_time":0.9725216395},
{"learn":[1.080573643],"iteration":233,"passed_time":0.2961985005,"remaining_time":0.9696070573},
{"learn":[1.079294445],"iteration":234,"passed_time":0.2969494973,"remaining_time":0.9666653849},
{"learn":[1.078426028],"iteration":235,"passed_time":0.2977215868,"remaining_time":0.9638105608},
{"learn":[1.077461664],"iteration":236,"passed_time":0.2985002367,"remaining_time":0.960994433},
{"learn":[1.074801478],"iteration":237,"passed_time":0.2992628993,"remaining_time":0.9581442406},
{"learn":[1.072651113],"iteration":238,"passed_time":0.3000394426,"remaining_time":0.9553557147},
{"learn":[1.071415311],"iteration":239,"passed_time":0.3008474633,"remaining_time":0.9526836339},
{"learn":[1.070754596],"iteration":240,"passed_time":0.3019944982,"remaining_time":0.951094706},
{"learn":[1.069228599],"iteration":241,"passed_time":0.3030516666,"remaining_time":0.9492279475},
{"learn":[1.066028399],"iteration":242,"passed_time":0.3039765242,"remaining_time":0.9469556742},
{"learn":[1.065002909],"iteration":243,"passed_time":0.3048250067,"remaining_time":0.9444578075},
{"learn":[1.063420358],"iteration":244,"passed_time":0.3056038982,"remaining_time":0.9417589516},
{"learn":[1.060643448],"iteration":245,"passed_time":0.3064307979,"remaining_time":0.9392228521},
{"learn":[1.059943176],"iteration":246,"passed_time":0.3073452058,"remaining_time":0.9369673682},
{"learn":[1.059141976],"iteration":247,"passed_time":0.3084291546,"remaining_time":0.9352367913},
{"learn":[1.056400778],"iteration":248,"passed_time":0.3098708225,"remaining_time":0.9345903121},
{"learn":[1.054984814],"iteration":249,"passed_time":0.3108216533,"remaining_time":0.9324649599},
{"learn":[1.051730607],"iteration":250,"passed_time":0.3116203365,"remaining_time":0.9298949485},
{"learn":[1.049733805],"iteration":251,"passed_time":0.3126134417,"remaining_time":0.9279160889},
{"learn":[1.047215021],"iteration":252,"passed_time":0.3135533994,"remaining_time":0.9257881003},
{"learn":[1.046566518],"iteration":253,"passed_time":0.3142759986,"remaining_time":0.9230310826},
{"learn":[1.04444515],"iteration":254,"passed_time":0.314996864,"remaining_time":0.9202849556},
{"learn":[1.043583678],"iteration":255,"passed_time":0.3161097659,"remaining_time":0.9186940072},
{"learn":[1.042016952],"iteration":256,"passed_time":0.3172873216,"remaining_time":0.9172936963},
{"learn":[1.041298096],"iteration":257,"passed_time":0.318382464,"remaining_time":0.9156580941},
{"learn":[1.038901998],"iteration":258,"passed_time":0.3194622001,"remaining_time":0.913982588},
{"learn":[1.037124377],"iteration":259,"passed_time":0.3205513421,"remaining_time":0.9123384353},
{"learn":[1.036283337],"iteration":260,"passed_time":0.3218099206,"remaining_time":0.911178281},
{"learn":[1.035504453],"iteration":261,"passed_time":0.3229158277,"remaining_time":0.9095873315},
{"learn":[1.034830915],"iteration":262,"passed_time":0.3239151205,"remaining_time":0.9077013073},
{"learn":[1.033668825],"iteration":263,"passed_time":0.3247135921,"remaining_time":0.9052621355},
{"learn":[1.03131957],"iteration":264,"passed_time":0.3254176712,"remaining_time":0.902573541},
{"learn":[1.03077443],"iteration":265,"passed_time":0.3261692713,"remaining_time":0.9000309968},
{"learn":[1.030045788],"iteration":266,"passed_time":0.3270259735,"remaining_time":0.8977904067},
{"learn":[1.028358585],"iteration":267,"passed_time":0.3277865112,"remaining_time":0.8952974857},
{"learn":[1.027653593],"iteration":268,"passed_time":0.3285303242,"remaining_time":0.8927719963},
{"learn":[1.02693386],"iteration":269,"passed_time":0.3292392044,"remaining_time":0.8901652562},
{"learn":[1.025492796],"iteration":270,"passed_time":0.3300172115,"remaining_time":0.8877584767},
{"learn":[1.023707569],"iteration":271,"passed_time":0.3311188931,"remaining_time":0.8862299787},
{"learn":[1.021989245],"iteration":272,"passed_time":0.3320001564,"remaining_time":0.8841176325},
{"learn":[1.019503473],"iteration":273,"passed_time":0.3328705177,"remaining_time":0.8819853862},
{"learn":[1.01881327],"iteration":274,"passed_time":0.3338688743,"remaining_time":0.8801997596},
{"learn":[1.017907627],"iteration":275,"passed_time":0.3349427512,"remaining_time":0.8786179416},
{"learn":[1.016748522],"iteration":276,"passed_time":0.3364054725,"remaining_time":0.8780547169},
{"learn":[1.016223126],"iteration":277,"passed_time":0.3376460837,"remaining_time":0.8769081741},
{"learn":[1.014095727],"iteration":278,"passed_time":0.3388366424,"remaining_time":0.8756316098},
{"learn":[1.013459067],"iteration":279,"passed_time":0.3395937273,"remaining_time":0.873241013},
{"learn":[1.012316016],"iteration":280,"passed_time":0.340314781,"remaining_time":0.8707698488},
{"learn":[1.011714136],"iteration":281,"passed_time":0.3410669038,"remaining_time":0.8683902019},
{"learn":[1.01026843],"iteration":282,"passed_time":0.3417525374,"remaining_time":0.8658536017},
{"learn":[1.009793309],"iteration":283,"passed_time":0.3424930227,"remaining_time":0.8634683249},
{"learn":[1.007780958],"iteration":284,"passed_time":0.3434980676,"remaining_time":0.8617583099},
{"learn":[1.006237949],"iteration":285,"passed_time":0.3442587369,"remaining_time":0.8594431403},
{"learn":[1.003158537],"iteration":286,"passed_time":0.345080165,"remaining_time":0.857289748},
{"learn":[1.000706058],"iteration":287,"passed_time":0.3458711252,"remaining_time":0.8550702817},
{"learn":[1.000085701],"iteration":288,"passed_time":0.3467495529,"remaining_time":0.8530758897},
{"learn":[0.9972526605],"iteration":289,"passed_time":0.3474480011,"remaining_time":0.8506485544},
{"learn":[0.9968390592],"iteration":290,"passed_time":0.3481352146,"remaining_time":0.848205729},
{"learn":[0.9963475089],"iteration":291,"passed_time":0.3488678119,"remaining_time":0.8458849685},
{"learn":[0.9957570093],"iteration":292,"passed_time":0.3497270185,"remaining_time":0.8438805531},
{"learn":[0.9951488666],"iteration":293,"passed_time":0.3506554932,"remaining_time":0.8420502659},
{"learn":[0.9939795253],"iteration":294,"passed_time":0.3521902736,"remaining_time":0.8416750606},
{"learn":[0.9902934497],"iteration":295,"passed_time":0.3534964452,"remaining_time":0.8407483021},
{"learn":[0.9896734755],"iteration":296,"passed_time":0.3546762814,"remaining_time":0.8395199523},
{"learn":[0.9893346638],"iteration":297,"passed_time":0.3554275154,"remaining_time":0.8372822678},
{"learn":[0.9865011681],"iteration":298,"passed_time":0.3563887131,"remaining_time":0.8355467822},
{"learn":[0.9852104548],"iteration":299,"passed_time":0.3571591549,"remaining_time":0.8333713614},
{"learn":[0.9835661929],"iteration":300,"passed_time":0.3582202038,"remaining_time":0.831880141},
{"learn":[0.9829711205],"iteration":301,"passed_time":0.3589544249,"remaining_time":0.8296363859},
{"learn":[0.9823736308],"iteration":302,"passed_time":0.359689416,"remaining_time":0.8274043661},
{"learn":[0.9818882913],"iteration":303,"passed_time":0.3605679831,"remaining_time":0.8255109088},
{"learn":[0.9815340177],"iteration":304,"passed_time":0.3614359506,"remaining_time":0.823599953},
{"learn":[0.9809774265],"iteration":305,"passed_time":0.3623339045,"remaining_time":0.8217638226},
{"learn":[0.9804915823],"iteration":306,"passed_time":0.3633520884,"remaining_time":0.8202052028},
{"learn":[0.9788959032],"iteration":307,"passed_time":0.3653368127,"remaining_time":0.82082167},
{"learn":[0.9774468608],"iteration":308,"passed_time":0.3675784905,"remaining_time":0.8219959124},
{"learn":[0.9768895057],"iteration":309,"passed_time":0.3700740981,"remaining_time":0.823713315},
{"learn":[0.9765934021],"iteration":310,"passed_time":0.3712327771,"remaining_time":0.8224417472},
{"learn":[0.972002776],"iteration":311,"passed_time":0.3723398708,"remaining_time":0.821057151},
{"learn":[0.9693883746],"iteration":312,"passed_time":0.3739083436,"remaining_time":0.8206870034},
{"learn":[0.9680975982],"iteration":313,"passed_time":0.3753041717,"remaining_time":0.8199320439},
{"learn":[0.9662879044],"iteration":314,"passed_time":0.38766289,"remaining_time":0.8430129513},
{"learn":[0.9645352432],"iteration":315,"passed_time":0.3901805231,"remaining_time":0.8445679677},
{"learn":[0.9591136317],"iteration":316,"passed_time":0.3965157255,"remaining_time":0.8543225253},
{"learn":[0.9581379264],"iteration":317,"passed_time":0.3998807116,"remaining_time":0.8576058029},
{"learn":[0.957619858],"iteration":318,"passed_time":0.4086331238,"remaining_time":0.8723484554},
{"learn":[0.9571708911],"iteration":319,"passed_time":0.4094319714,"remaining_time":0.8700429393},
{"learn":[0.956667911],"iteration":320,"passed_time":0.4107421246,"remaining_time":0.8688283571},
{"learn":[0.9534211427],"iteration":321,"passed_time":0.4123769596,"remaining_time":0.8682968279},
{"learn":[0.9531435603],"iteration":322,"passed_time":0.4151272619,"remaining_time":0.8700964591},
{"learn":[0.9522160545],"iteration":323,"passed_time":0.4172757278,"remaining_time":0.8706123209},
{"learn":[0.9519465181],"iteration":324,"passed_time":0.4191756005,"remaining_time":0.8705954779},
{"learn":[0.951400811],"iteration":325,"passed_time":0.4214732845,"remaining_time":0.8713895515},
{"learn":[0.9508282514],"iteration":326,"passed_time":0.423097477,"remaining_time":0.8707785994},
{"learn":[0.9492534793],"iteration":327,"passed_time":0.4244548366,"remaining_time":0.8696147873},
{"learn":[0.9489892325],"iteration":328,"passed_time":0.4259264316,"remaining_time":0.8686827829},
{"learn":[0.9485092282],"iteration":329,"passed_time":0.4270971758,"remaining_time":0.8671366902},
{"learn":[0.9477812436],"iteration":330,"passed_time":0.4281224251,"remaining_time":0.8652987987},
{"learn":[0.9470629847],"iteration":331,"passed_time":0.4294333238,"remaining_time":0.8640405431},
{"learn":[0.946144978],"iteration":332,"passed_time":0.4309502653,"remaining_time":0.8631946755},
{"learn":[0.9452241487],"iteration":333,"passed_time":0.4321066238,"remaining_time":0.8616257827},
{"learn":[0.9395305409],"iteration":334,"passed_time":0.4330920408,"remaining_time":0.8597200213},
{"learn":[0.9383143876],"iteration":335,"passed_time":0.4340537702,"remaining_time":0.8577729267},
{"learn":[0.9366678644],"iteration":336,"passed_time":0.43510004,"remaining_time":0.8559980015},
{"learn":[0.9357760665],"iteration":337,"passed_time":0.4371366951,"remaining_time":0.8561671365},
{"learn":[0.9330276427],"iteration":338,"passed_time":0.4389099206,"remaining_time":0.8558096093},
{"learn":[0.9307973972],"iteration":339,"passed_time":0.4402070125,"remaining_time":0.8545194949},
{"learn":[0.9299269156],"iteration":340,"passed_time":0.4416176691,"remaining_time":0.8534488092},
{"learn":[0.9283447176],"iteration":341,"passed_time":0.4431029531,"remaining_time":0.8525197168},
{"learn":[0.9281155449],"iteration":342,"passed_time":0.4449533882,"remaining_time":0.8522868107},
{"learn":[0.9274659294],"iteration":343,"passed_time":0.4463661247,"remaining_time":0.8512098193},
{"learn":[0.9248804699],"iteration":344,"passed_time":0.4475853921,"remaining_time":0.8497635705},
{"learn":[0.924499613],"iteration":345,"passed_time":0.4490541843,"remaining_time":0.848790279},
{"learn":[0.9201444555],"iteration":346,"passed_time":0.4507185801,"remaining_time":0.848182227},
{"learn":[0.9185622945],"iteration":347,"passed_time":0.4534280313,"remaining_time":0.8495260816},
{"learn":[0.9173016017],"iteration":348,"passed_time":0.4560318142,"remaining_time":0.8506496019},
{"learn":[0.9170808476],"iteration":349,"passed_time":0.4579799378,"remaining_time":0.8505341702},
{"learn":[0.9156795301],"iteration":350,"passed_time":0.4640524435,"remaining_time":0.8580342901},
{"learn":[0.9154548286],"iteration":351,"passed_time":0.4696168119,"remaining_time":0.8645218583},
{"learn":[0.9143114696],"iteration":352,"passed_time":0.4708560493,"remaining_time":0.8630137787},
{"learn":[0.9124849847],"iteration":353,"passed_time":0.472342261,"remaining_time":0.8619579113},
{"learn":[0.9118545993],"iteration":354,"passed_time":0.473608586,"remaining_time":0.8605001069},
{"learn":[0.909848067],"iteration":355,"passed_time":0.4747834401,"remaining_time":0.8588779084},
{"learn":[0.9096143926],"iteration":356,"passed_time":0.4760997981,"remaining_time":0.8575130817},
{"learn":[0.9086762464],"iteration":357,"passed_time":0.4772587404,"remaining_time":0.8558662328},
{"learn":[0.9080007251],"iteration":358,"passed_time":0.4787058127,"remaining_time":0.8547365624},
{"learn":[0.9055488483],"iteration":359,"passed_time":0.479956878,"remaining_time":0.853256672},
{"learn":[0.9002470199],"iteration":360,"passed_time":0.4823381904,"remaining_time":0.8537786805},
{"learn":[0.8997743509],"iteration":361,"passed_time":0.4846533145,"remaining_time":0.8541679963},
{"learn":[0.8985072411],"iteration":362,"passed_time":0.4860091448,"remaining_time":0.8528590227},
{"learn":[0.8981352869],"iteration":363,"passed_time":0.4873480972,"remaining_time":0.8515203017},
{"learn":[0.8967741439],"iteration":364,"passed_time":0.4884957232,"remaining_time":0.8498487239},
{"learn":[0.8965642173],"iteration":365,"passed_time":0.4898458081,"remaining_time":0.8485307167},
{"learn":[0.8946837645],"iteration":366,"passed_time":0.4911848777,"remaining_time":0.8471935357},
{"learn":[0.89334398],"iteration":367,"passed_time":0.4926055473,"remaining_time":0.8459964835},
{"learn":[0.8917098135],"iteration":368,"passed_time":0.4948640647,"remaining_time":0.8462309616},
{"learn":[0.8905886455],"iteration":369,"passed_time":0.4969165438,"remaining_time":0.8461011421},
{"learn":[0.8901284864],"iteration":370,"passed_time":0.4995434583,"remaining_time":0.846934866},
{"learn":[0.8885055686],"iteration":371,"passed_time":0.5009434341,"remaining_time":0.8456787006},
{"learn":[0.8865526329],"iteration":372,"passed_time":0.5021638753,"remaining_time":0.8441199727},
{"learn":[0.8853881041],"iteration":373,"passed_time":0.5032926295,"remaining_time":0.8424095885},
{"learn":[0.8814717217],"iteration":374,"passed_time":0.5050753976,"remaining_time":0.8417923294},
{"learn":[0.8802969153],"iteration":375,"passed_time":0.5061326594,"remaining_time":0.839964839},
{"learn":[0.8792384984],"iteration":376,"passed_time":0.5077877393,"remaining_time":0.8391293411},
{"learn":[0.8788150379],"iteration":377,"passed_time":0.5092651891,"remaining_time":0.8379972159},
{"learn":[0.8772069682],"iteration":378,"passed_time":0.5106677536,"remaining_time":0.8367405673},
{"learn":[0.876345275],"iteration":379,"passed_time":0.5117122441,"remaining_time":0.8348989245},
{"learn":[0.8715686048],"iteration":380,"passed_time":0.5127485019,"remaining_time":0.8330480911},
{"learn":[0.867622711],"iteration":381,"passed_time":0.5137755884,"remaining_time":0.8311866849},
{"learn":[0.865381601],"iteration":382,"passed_time":0.5147613349,"remaining_time":0.8292630382},
{"learn":[0.8636945765],"iteration":383,"passed_time":0.5158542823,"remaining_time":0.8275162446},
{"learn":[0.8598931429],"iteration":384,"passed_time":0.5177728056,"remaining_time":0.8270916246},
{"learn":[0.8551572137],"iteration":385,"passed_time":0.5197693179,"remaining_time":0.8267833192},
{"learn":[0.8514485871],"iteration":386,"passed_time":0.5217495745,"remaining_time":0.8264405405},
{"learn":[0.8478169264],"iteration":387,"passed_time":0.5228159666,"remaining_time":0.8246478648},
{"learn":[0.843961209],"iteration":388,"passed_time":0.5238242441,"remaining_time":0.8227676431},
{"learn":[0.8405841852],"iteration":389,"passed_time":0.5249485752,"remaining_time":0.8210734124},
{"learn":[0.8393663685],"iteration":390,"passed_time":0.5261169544,"remaining_time":0.819450704},
{"learn":[0.8381157228],"iteration":391,"passed_time":0.5303557679,"remaining_time":0.8225926195},
{"learn":[0.8379149469],"iteration":392,"passed_time":0.5326012067,"remaining_time":0.8226181487},
{"learn":[0.8343367293],"iteration":393,"passed_time":0.5338994541,"remaining_time":0.8211753025},
{"learn":[0.8339579705],"iteration":394,"passed_time":0.5356935124,"remaining_time":0.820492595},
{"learn":[0.8324234407],"iteration":395,"passed_time":0.5377569079,"remaining_time":0.8202150818},
{"learn":[0.8287718251],"iteration":396,"passed_time":0.5397715252,"remaining_time":0.8198544829},
{"learn":[0.8254028851],"iteration":397,"passed_time":0.5412642424,"remaining_time":0.8186961656},
{"learn":[0.8244884554],"iteration":398,"passed_time":0.5424564465,"remaining_time":0.8170835197},
{"learn":[0.8213567597],"iteration":399,"passed_time":0.5435405431,"remaining_time":0.8153108147},
{"learn":[0.8198745405],"iteration":400,"passed_time":0.545910333,"remaining_time":0.8154620685},
{"learn":[0.8195486278],"iteration":401,"passed_time":0.546825467,"remaining_time":0.8134368887},
{"learn":[0.8182450859],"iteration":402,"passed_time":0.5480714491,"remaining_time":0.8119073328},
{"learn":[0.8169025519],"iteration":403,"passed_time":0.549397063,"remaining_time":0.8104966573},
{"learn":[0.8155939643],"iteration":404,"passed_time":0.5510324918,"remaining_time":0.809541562},
{"learn":[0.8144546388],"iteration":405,"passed_time":0.5519510073,"remaining_time":0.8075342324},
{"learn":[0.8104464519],"iteration":406,"passed_time":0.5533138047,"remaining_time":0.8061795729},
{"learn":[0.8089427602],"iteration":407,"passed_time":0.5544696687,"remaining_time":0.8045246174},
{"learn":[0.8074681864],"iteration":408,"passed_time":0.5557853807,"remaining_time":0.8031030806},
{"learn":[0.8040576153],"iteration":409,"passed_time":0.557049879,"remaining_time":0.8016083625},
{"learn":[0.8029750862],"iteration":410,"passed_time":0.5588038473,"remaining_time":0.8008162192},
{"learn":[0.8026842441],"iteration":411,"passed_time":0.5605198028,"remaining_time":0.7999651555},
{"learn":[0.8016321391],"iteration":412,"passed_time":0.5623947301,"remaining_time":0.7993358512},
{"learn":[0.8011474681],"iteration":413,"passed_time":0.5641641435,"remaining_time":0.798551179},
{"learn":[0.7971661852],"iteration":414,"passed_time":0.5660773542,"remaining_time":0.7979644631},
{"learn":[0.7939416391],"iteration":415,"passed_time":0.5671321938,"remaining_time":0.796166349},
{"learn":[0.7925036763],"iteration":416,"passed_time":0.5687503119,"remaining_time":0.795159309},
{"learn":[0.7914697993],"iteration":417,"passed_time":0.5694913862,"remaining_time":0.792928198},
{"learn":[0.7912310431],"iteration":418,"passed_time":0.5707536546,"remaining_time":0.7914269053},
{"learn":[0.790777178],"iteration":419,"passed_time":0.5725617098,"remaining_time":0.7906804563},
{"learn":[0.7882472784],"iteration":420,"passed_time":0.5737306118,"remaining_time":0.7890499388},
{"learn":[0.7851462573],"iteration":421,"passed_time":0.5748506874,"remaining_time":0.787354733},
{"learn":[0.7815925933],"iteration":422,"passed_time":0.5758012149,"remaining_time":0.7854309716},
{"learn":[0.7801912696],"iteration":423,"passed_time":0.5768000854,"remaining_time":0.7835774745},
{"learn":[0.7770878578],"iteration":424,"passed_time":0.5776447302,"remaining_time":0.7815193408},
{"learn":[0.7757770111],"iteration":425,"passed_time":0.5790046287,"remaining_time":0.7801611664},
{"learn":[0.7744374843],"iteration":426,"passed_time":0.5803797568,"remaining_time":0.7788234207},
{"learn":[0.7736318438],"iteration":427,"passed_time":0.5827229541,"remaining_time":0.7787792751},
{"learn":[0.7723219934],"iteration":428,"passed_time":0.5847428418,"remaining_time":0.7782940855},
{"learn":[0.7713395635],"iteration":429,"passed_time":0.585969109,"remaining_time":0.7767497491},
{"learn":[0.7700534829],"iteration":430,"passed_time":0.5873829038,"remaining_time":0.77545446},
{"learn":[0.7671413319],"iteration":431,"passed_time":0.5886910559,"remaining_time":0.7740197217},
{"learn":[0.7656901314],"iteration":432,"passed_time":0.5897403507,"remaining_time":0.7722466024},
{"learn":[0.7644312429],"iteration":433,"passed_time":0.5907470777,"remaining_time":0.7704213041},
{"learn":[0.7615175588],"iteration":434,"passed_time":0.5920413502,"remaining_time":0.768973248},
{"learn":[0.7594218778],"iteration":435,"passed_time":0.5931711078,"remaining_time":0.7673130844},
{"learn":[0.7591789094],"iteration":436,"passed_time":0.5943687046,"remaining_time":0.7657427476},
{"learn":[0.7583216205],"iteration":437,"passed_time":0.5954305207,"remaining_time":0.7639998918},
{"learn":[0.7571139932],"iteration":438,"passed_time":0.5966965573,"remaining_time":0.7625211131},
{"learn":[0.7569501913],"iteration":439,"passed_time":0.5988729675,"remaining_time":0.7622019586},
{"learn":[0.7537812316],"iteration":440,"passed_time":0.6006890696,"remaining_time":0.7614176642},
{"learn":[0.7518810155],"iteration":441,"passed_time":0.6020614567,"remaining_time":0.7600685358},
{"learn":[0.7488076508],"iteration":442,"passed_time":0.6031501276,"remaining_time":0.7583625758},
{"learn":[0.7485215903],"iteration":443,"passed_time":0.604114768,"remaining_time":0.7565040788},
{"learn":[0.7475403998],"iteration":444,"passed_time":0.6050761507,"remaining_time":0.7546455363},
{"learn":[0.7473446017],"iteration":445,"passed_time":0.6064531515,"remaining_time":0.7533072779},
{"learn":[0.7450362658],"iteration":446,"passed_time":0.60814121,"remaining_time":0.7523536669},
{"learn":[0.7430285046],"iteration":447,"passed_time":0.6096834713,"remaining_time":0.7512171343},
{"learn":[0.7421289539],"iteration":448,"passed_time":0.6108714123,"remaining_time":0.7496439825},
{"learn":[0.7409197598],"iteration":449,"passed_time":0.6126364903,"remaining_time":0.7487779326},
{"learn":[0.7382123112],"iteration":450,"passed_time":0.6145106587,"remaining_time":0.7480406909},
{"learn":[0.7372663374],"iteration":451,"passed_time":0.6152509135,"remaining_time":0.7459236739},
{"learn":[0.7348744254],"iteration":452,"passed_time":0.6161919273,"remaining_time":0.7440551529},
{"learn":[0.7345626472],"iteration":453,"passed_time":0.6171160494,"remaining_time":0.742170403},
{"learn":[0.7335914946],"iteration":454,"passed_time":0.6179970843,"remaining_time":0.7402382658},
{"learn":[0.7315609381],"iteration":455,"passed_time":0.619115806,"remaining_time":0.7385942949},
{"learn":[0.7301953452],"iteration":456,"passed_time":0.619937517,"remaining_time":0.7365997193},
{"learn":[0.7274834579],"iteration":457,"passed_time":0.6222569021,"remaining_time":0.7363826221},
{"learn":[0.7258543505],"iteration":458,"passed_time":0.62429153,"remaining_time":0.7358207358},
{"learn":[0.7251484235],"iteration":459,"passed_time":0.6266016249,"remaining_time":0.7355758205},
{"learn":[0.7216338039],"iteration":460,"passed_time":0.6287157239,"remaining_time":0.7350927879},
{"learn":[0.718841557],"iteration":461,"passed_time":0.6298169,"remaining_time":0.7334231433},
{"learn":[0.716293471],"iteration":462,"passed_time":0.6308222432,"remaining_time":0.7316448048},
{"learn":[0.715367878],"iteration":463,"passed_time":0.6318358189,"remaining_time":0.7298793081},
{"learn":[0.714962622],"iteration":464,"passed_time":0.633136018,"remaining_time":0.7284468164},
{"learn":[0.712446286],"iteration":465,"passed_time":0.6344482861,"remaining_time":0.7270287227},
{"learn":[0.7122314586],"iteration":466,"passed_time":0.6359107963,"remaining_time":0.7257825576},
{"learn":[0.7115112782],"iteration":467,"passed_time":0.6374458189,"remaining_time":0.7246178967},
{"learn":[0.7103263931],"iteration":468,"passed_time":0.6384902671,"remaining_time":0.7228962299},
{"learn":[0.7101780732],"iteration":469,"passed_time":0.6402632399,"remaining_time":0.7219989727},
{"learn":[0.7090558605],"iteration":470,"passed_time":0.6418019191,"remaining_time":0.7208348518},
{"learn":[0.7063180272],"iteration":471,"passed_time":0.6426567814,"remaining_time":0.7189041961},
{"learn":[0.7045122791],"iteration":472,"passed_time":0.6436288671,"remaining_time":0.7171086955},
{"learn":[0.7020857172],"iteration":473,"passed_time":0.6444833933,"remaining_time":0.7151862128},
{"learn":[0.6998575918],"iteration":474,"passed_time":0.6454913658,"remaining_time":0.7134378254},
{"learn":[0.699712754],"iteration":475,"passed_time":0.6468895027,"remaining_time":0.7121220576},
{"learn":[0.6985113136],"iteration":476,"passed_time":0.6490810442,"remaining_time":0.7116758618},
{"learn":[0.6978310488],"iteration":477,"passed_time":0.6505078903,"remaining_time":0.7103872777},
{"learn":[0.6968992998],"iteration":478,"passed_time":0.6520238468,"remaining_time":0.70919504},
{"learn":[0.6960247524],"iteration":479,"passed_time":0.6528738108,"remaining_time":0.7072799617},
{"learn":[0.6958848413],"iteration":480,"passed_time":0.6542248346,"remaining_time":0.7059099566},
{"learn":[0.6951242541],"iteration":481,"passed_time":0.6554162516,"remaining_time":0.7043685027},
{"learn":[0.6931179623],"iteration":482,"passed_time":0.6566745978,"remaining_time":0.7029001389},
{"learn":[0.6916929795],"iteration":483,"passed_time":0.6577662776,"remaining_time":0.7012549571},
{"learn":[0.6915561583],"iteration":484,"passed_time":0.6591808846,"remaining_time":0.6999549599},
{"learn":[0.6904360581],"iteration":485,"passed_time":0.6607262658,"remaining_time":0.6987927996},
{"learn":[0.6886180376],"iteration":486,"passed_time":0.6621812789,"remaining_time":0.6975338729},
{"learn":[0.6882500259],"iteration":487,"passed_time":0.6637316273,"remaining_time":0.6963741663},
{"learn":[0.6859957178],"iteration":488,"passed_time":0.665359434,"remaining_time":0.6952938053},
{"learn":[0.6838174318],"iteration":489,"passed_time":0.6666814119,"remaining_time":0.6938928981},
{"learn":[0.6830332889],"iteration":490,"passed_time":0.6677282867,"remaining_time":0.6922071241},
{"learn":[0.6798444226],"iteration":491,"passed_time":0.6690187399,"remaining_time":0.6907754469},
{"learn":[0.6792234812],"iteration":492,"passed_time":0.6701521979,"remaining_time":0.6891828891},
{"learn":[0.6771753099],"iteration":493,"passed_time":0.6710730451,"remaining_time":0.6873744146},
{"learn":[0.6756220888],"iteration":494,"passed_time":0.6724118308,"remaining_time":0.6859959082},
{"learn":[0.6734195722],"iteration":495,"passed_time":0.6736113442,"remaining_time":0.6844760433},
{"learn":[0.6731967894],"iteration":496,"passed_time":0.67568513,"remaining_time":0.6838422945},
{"learn":[0.6720422667],"iteration":497,"passed_time":0.6770938855,"remaining_time":0.6825323906},
{"learn":[0.6718832492],"iteration":498,"passed_time":0.6780059262,"remaining_time":0.6807233848},
{"learn":[0.6700108832],"iteration":499,"passed_time":0.6793904051,"remaining_time":0.6793904051},
{"learn":[0.6688944076],"iteration":500,"passed_time":0.6806102864,"remaining_time":0.6778932792},
{"learn":[0.6686264568],"iteration":501,"passed_time":0.6815891052,"remaining_time":0.6761581164},
{"learn":[0.6685045356],"iteration":502,"passed_time":0.6824150727,"remaining_time":0.6742749327},
{"learn":[0.6682402384],"iteration":503,"passed_time":0.6833671563,"remaining_time":0.6725200585},
{"learn":[0.6659445318],"iteration":504,"passed_time":0.6842383531,"remaining_time":0.6706890788},
{"learn":[0.6639784614],"iteration":505,"passed_time":0.6852038334,"remaining_time":0.6689539402},
{"learn":[0.6618535074],"iteration":506,"passed_time":0.6863832891,"remaining_time":0.6674299044},
{"learn":[0.6608978118],"iteration":507,"passed_time":0.6875540916,"remaining_time":0.6658988447},
{"learn":[0.6588737672],"iteration":508,"passed_time":0.6892867339,"remaining_time":0.6649111716},
{"learn":[0.6587208581],"iteration":509,"passed_time":0.6913698977,"remaining_time":0.6642573527},
{"learn":[0.6568855128],"iteration":510,"passed_time":0.6925424346,"remaining_time":0.6627265177},
{"learn":[0.6567638922],"iteration":511,"passed_time":0.6940203338,"remaining_time":0.6614881307},
{"learn":[0.655405409],"iteration":512,"passed_time":0.6957680479,"remaining_time":0.6605049499},
{"learn":[0.6540190757],"iteration":513,"passed_time":0.6970455559,"remaining_time":0.6590742026},
{"learn":[0.6539234715],"iteration":514,"passed_time":0.6980092096,"remaining_time":0.657348479},
{"learn":[0.6522153572],"iteration":515,"passed_time":0.6997525404,"remaining_time":0.6563570341},
{"learn":[0.6511525614],"iteration":516,"passed_time":0.7009197292,"remaining_time":0.6548244279},
{"learn":[0.6503072621],"iteration":517,"passed_time":0.7023431465,"remaining_time":0.6535316537},
{"learn":[0.6501071116],"iteration":518,"passed_time":0.7033055503,"remaining_time":0.651811117},
{"learn":[0.6490389919],"iteration":519,"passed_time":0.7057839773,"remaining_time":0.6514929021},
{"learn":[0.6479351064],"iteration":520,"passed_time":0.7070125938,"remaining_time":0.6500173367},
{"learn":[0.6449027043],"iteration":521,"passed_time":0.7093548733,"remaining_time":0.6495625085},
{"learn":[0.6447758403],"iteration":522,"passed_time":0.7112120499,"remaining_time":0.6486580264},
{"learn":[0.6438250811],"iteration":523,"passed_time":0.7121842946,"remaining_time":0.6469460386},
{"learn":[0.6421341825],"iteration":524,"passed_time":0.7131220946,"remaining_time":0.6452057046},
{"learn":[0.6404821605],"iteration":525,"passed_time":0.7142110394,"remaining_time":0.6436046248},
{"learn":[0.6396945018],"iteration":526,"passed_time":0.7151093493,"remaining_time":0.6418343875},
{"learn":[0.6366054838],"iteration":527,"passed_time":0.716993618,"remaining_time":0.6409488403},
{"learn":[0.636359193],"iteration":528,"passed_time":0.718923261,"remaining_time":0.6400999167},
{"learn":[0.6335416173],"iteration":529,"passed_time":0.7202144886,"remaining_time":0.6386807729},
{"learn":[0.6325669805],"iteration":530,"passed_time":0.7217994426,"remaining_time":0.6375215416},
{"learn":[0.6319956245],"iteration":531,"passed_time":0.7236389559,"remaining_time":0.6365846454},
{"learn":[0.6318898335],"iteration":532,"passed_time":0.7249694546,"remaining_time":0.6351983777},
{"learn":[0.6316685857],"iteration":533,"passed_time":0.7259963028,"remaining_time":0.6335473354},
{"learn":[0.6308611696],"iteration":534,"passed_time":0.726909859,"remaining_time":0.6318001578},
{"learn":[0.630194105],"iteration":535,"passed_time":0.7279671768,"remaining_time":0.6301805411},
{"learn":[0.6291079514],"iteration":536,"passed_time":0.7294284976,"remaining_time":0.6289113489},
{"learn":[0.6275598332],"iteration":537,"passed_time":0.730993325,"remaining_time":0.6277303274},
{"learn":[0.6268086992],"iteration":538,"passed_time":0.7335537035,"remaining_time":0.6273993643},
{"learn":[0.625855026],"iteration":539,"passed_time":0.7355232988,"remaining_time":0.6265568841},
{"learn":[0.6257504454],"iteration":540,"passed_time":0.7373590182,"remaining_time":0.6255966532},
{"learn":[0.6241631125],"iteration":541,"passed_time":0.738693483,"remaining_time":0.6242096221},
{"learn":[0.6236356281],"iteration":542,"passed_time":0.739519481,"remaining_time":0.6223948487},
{"learn":[0.6212192942],"iteration":543,"passed_time":0.7404350905,"remaining_time":0.6206588259},
{"learn":[0.620591396],"iteration":544,"passed_time":0.7412731927,"remaining_time":0.6188611058},
{"learn":[0.6203713645],"iteration":545,"passed_time":0.7421753348,"remaining_time":0.6171201502},
{"learn":[0.6202790821],"iteration":546,"passed_time":0.743695915,"remaining_time":0.6158944232},
{"learn":[0.6195077059],"iteration":547,"passed_time":0.7449802406,"remaining_time":0.6144727532},
{"learn":[0.6178734939],"iteration":548,"passed_time":0.746253612,"remaining_time":0.6130425847},
{"learn":[0.6168128878],"iteration":549,"passed_time":0.7481750058,"remaining_time":0.6121431866},
{"learn":[0.615776082],"iteration":550,"passed_time":0.7494091205,"remaining_time":0.6106800274},
{"learn":[0.6156559112],"iteration":551,"passed_time":0.7512492243,"remaining_time":0.6097095153},
{"learn":[0.6154270285],"iteration":552,"passed_time":0.7527906889,"remaining_time":0.6084944629},
{"learn":[0.6138697551],"iteration":553,"passed_time":0.7540249492,"remaining_time":0.6070309158},
{"learn":[0.6129229096],"iteration":554,"passed_time":0.7552279075,"remaining_time":0.605543097},
{"learn":[0.6118753263],"iteration":555,"passed_time":0.7563844399,"remaining_time":0.604019229},
{"learn":[0.6117584634],"iteration":556,"passed_time":0.7574662021,"remaining_time":0.6024372128},
{"learn":[0.6103373572],"iteration":557,"passed_time":0.7585810801,"remaining_time":0.6008832211},
{"learn":[0.6086967474],"iteration":558,"passed_time":0.7601801338,"remaining_time":0.599712771},
{"learn":[0.6085700572],"iteration":559,"passed_time":0.76202932,"remaining_time":0.5987373229},
{"learn":[0.6059245819],"iteration":560,"passed_time":0.7632558361,"remaining_time":0.597271501},
{"learn":[0.6053256954],"iteration":561,"passed_time":0.7648843762,"remaining_time":0.5961198519},
{"learn":[0.6036453368],"iteration":562,"passed_time":0.7665322413,"remaining_time":0.5949815088},
{"learn":[0.6027191589],"iteration":563,"passed_time":0.7678486315,"remaining_time":0.5935851123},
{"learn":[0.6010663278],"iteration":564,"passed_time":0.7689306998,"remaining_time":0.5920085919},
{"learn":[0.6003267949],"iteration":565,"passed_time":0.7698126491,"remaining_time":0.5902803705},
{"learn":[0.5984381812],"iteration":566,"passed_time":0.7709599862,"remaining_time":0.5887578025},
{"learn":[0.5970693345],"iteration":567,"passed_time":0.7720670627,"remaining_time":0.587205935},
{"learn":[0.5966366798],"iteration":568,"passed_time":0.7734214864,"remaining_time":0.5858429888},
{"learn":[0.5948377515],"iteration":569,"passed_time":0.7750633772,"remaining_time":0.5846969337},
{"learn":[0.5926420211],"iteration":570,"passed_time":0.776926317,"remaining_time":0.5837152189},
{"learn":[0.5907021385],"iteration":571,"passed_time":0.7782999329,"remaining_time":0.5823642855},
{"learn":[0.5897523928],"iteration":572,"passed_time":0.7799234659,"remaining_time":0.5811995112},
{"learn":[0.58841927],"iteration":573,"passed_time":0.7815379153,"remaining_time":0.580026397},
{"learn":[0.5875837619],"iteration":574,"passed_time":0.7825709132,"remaining_time":0.5784219794},
{"learn":[0.5860354869],"iteration":575,"passed_time":0.7836149931,"remaining_time":0.5768277033},
{"learn":[0.5842605912],"iteration":576,"passed_time":0.7848587848,"remaining_time":0.5753817435},
{"learn":[0.5833506981],"iteration":577,"passed_time":0.7859836169,"remaining_time":0.5738496304},
{"learn":[0.5832258144],"iteration":578,"passed_time":0.7869677051,"remaining_time":0.572216587},
{"learn":[0.5815760523],"iteration":579,"passed_time":0.7881110434,"remaining_time":0.5707011004},
{"learn":[0.5808360454],"iteration":580,"passed_time":0.7904670298,"remaining_time":0.5700614208},
{"learn":[0.5792460705],"iteration":581,"passed_time":0.791670267,"remaining_time":0.5685879237},
{"learn":[0.5784769814],"iteration":582,"passed_time":0.7925832949,"remaining_time":0.566907777},
{"learn":[0.5783456709],"iteration":583,"passed_time":0.7935169012,"remaining_time":0.5652449159},
{"learn":[0.5769323928],"iteration":584,"passed_time":0.79451975,"remaining_time":0.5636336688},
{"learn":[0.5764499223],"iteration":585,"passed_time":0.7963353177,"remaining_time":0.5625986716},
{"learn":[0.5749908931],"iteration":586,"passed_time":0.7976522391,"remaining_time":0.5612101784},
{"learn":[0.5743032636],"iteration":587,"passed_time":0.7986004838,"remaining_time":0.5595636043},
{"learn":[0.5728738335],"iteration":588,"passed_time":0.7995037003,"remaining_time":0.557887981},
{"learn":[0.5717088103],"iteration":589,"passed_time":0.8006598105,"remaining_time":0.5563907158},
{"learn":[0.5701688318],"iteration":590,"passed_time":0.8016405304,"remaining_time":0.5547732266},
{"learn":[0.5689659916],"iteration":591,"passed_time":0.8027021054,"remaining_time":0.5532136132},
{"learn":[0.5683055492],"iteration":592,"passed_time":0.8044857607,"remaining_time":0.5521512725},
{"learn":[0.5677026422],"iteration":593,"passed_time":0.8062111448,"remaining_time":0.5510466747},
{"learn":[0.5672144648],"iteration":594,"passed_time":0.807722497,"remaining_time":0.5497943047},
{"learn":[0.5658534587],"iteration":595,"passed_time":0.8090263726,"remaining_time":0.548400427},
{"learn":[0.5646933086],"iteration":596,"passed_time":0.8101339374,"remaining_time":0.5468743329},
{"learn":[0.5646089505],"iteration":597,"passed_time":0.8111486336,"remaining_time":0.5452872086},
{"learn":[0.5644465143],"iteration":598,"passed_time":0.8120920863,"remaining_time":0.5436543015},
{"learn":[0.5642337642],"iteration":599,"passed_time":0.813145782,"remaining_time":0.542097188},
{"learn":[0.5637442412],"iteration":600,"passed_time":0.8141625293,"remaining_time":0.54051722},
{"learn":[0.5630869528],"iteration":601,"passed_time":0.8151340656,"remaining_time":0.5389092327},
{"learn":[0.5618340592],"iteration":602,"passed_time":0.8160576666,"remaining_time":0.5372717971},
{"learn":[0.5617229936],"iteration":603,"passed_time":0.8172185966,"remaining_time":0.5357923249},
{"learn":[0.5600408632],"iteration":604,"passed_time":0.8188354309,"remaining_time":0.5346115623},
{"learn":[0.5586969024],"iteration":605,"passed_time":0.8206005323,"remaining_time":0.5335257586},
{"learn":[0.5582573251],"iteration":606,"passed_time":0.8219392097,"remaining_time":0.53216163},
{"learn":[0.5570947072],"iteration":607,"passed_time":0.8233611237,"remaining_time":0.5308512508},
{"learn":[0.5569951428],"iteration":608,"passed_time":0.8243458119,"remaining_time":0.5292597906},
{"learn":[0.5559216708],"iteration":609,"passed_time":0.8254943912,"remaining_time":0.5277751025},
{"learn":[0.5548877143],"iteration":610,"passed_time":0.826378831,"remaining_time":0.5261233474},
{"learn":[0.5540360009],"iteration":611,"passed_time":0.8272703389,"remaining_time":0.5244785809},
{"learn":[0.553170347],"iteration":612,"passed_time":0.8281668845,"remaining_time":0.5228394523},
{"learn":[0.5521279769],"iteration":613,"passed_time":0.8290456294,"remaining_time":0.521191552},
{"learn":[0.5509876255],"iteration":614,"passed_time":0.8298950274,"remaining_time":0.5195277814},
{"learn":[0.5504158528],"iteration":615,"passed_time":0.8305524195,"remaining_time":0.5177469628},
{"learn":[0.550321269],"iteration":616,"passed_time":0.8317056558,"remaining_time":0.5162775789},
{"learn":[0.5502468983],"iteration":617,"passed_time":0.8326142133,"remaining_time":0.5146579765},
{"learn":[0.5501744766],"iteration":618,"passed_time":0.8336310262,"remaining_time":0.5131073037},
{"learn":[0.5495979723],"iteration":619,"passed_time":0.834575361,"remaining_time":0.5115139309},
{"learn":[0.5480453194],"iteration":620,"passed_time":0.8364502327,"remaining_time":0.5104905607},
{"learn":[0.5473166731],"iteration":621,"passed_time":0.8381340352,"remaining_time":0.5093483365},
{"learn":[0.547243782],"iteration":622,"passed_time":0.8394622062,"remaining_time":0.5079891681},
{"learn":[0.5471403551],"iteration":623,"passed_time":0.8403009728,"remaining_time":0.5063352016},
{"learn":[0.5460923978],"iteration":624,"passed_time":0.8411742857,"remaining_time":0.5047045714},
{"learn":[0.5454028933],"iteration":625,"passed_time":0.8421160739,"remaining_time":0.503117271},
{"learn":[0.5445968893],"iteration":626,"passed_time":0.843021387,"remaining_time":0.5015103307},
{"learn":[0.5435283909],"iteration":627,"passed_time":0.8438712583,"remaining_time":0.4998727836},
{"learn":[0.5434274807],"iteration":628,"passed_time":0.8447676034,"remaining_time":0.4982651524},
{"learn":[0.5431706796],"iteration":629,"passed_time":0.8456463283,"remaining_time":0.4966494309},
{"learn":[0.5430313323],"iteration":630,"passed_time":0.8469114794,"remaining_time":0.495262022},
{"learn":[0.5421229574],"iteration":631,"passed_time":0.8479436124,"remaining_time":0.4937393186},
{"learn":[0.5420361678],"iteration":632,"passed_time":0.8492816176,"remaining_time":0.4923955034},
{"learn":[0.5414098913],"iteration":633,"passed_time":0.850592773,"remaining_time":0.4910362065},
{"learn":[0.5413120145],"iteration":634,"passed_time":0.8519129954,"remaining_time":0.4896822729},
{"learn":[0.5412336097],"iteration":635,"passed_time":0.8529398468,"remaining_time":0.4881605413},
{"learn":[0.5405473497],"iteration":636,"passed_time":0.854037783,"remaining_time":0.4866808717},
{"learn":[0.5388816736],"iteration":637,"passed_time":0.8548233572,"remaining_time":0.4850251651},
{"learn":[0.5388006929],"iteration":638,"passed_time":0.85563927,"remaining_time":0.4833893215},
{"learn":[0.5374299008],"iteration":639,"passed_time":0.8564904923,"remaining_time":0.4817759019},
{"learn":[0.5361706426],"iteration":640,"passed_time":0.8573027774,"remaining_time":0.4801430532},
{"learn":[0.5348700144],"iteration":641,"passed_time":0.8580649417,"remaining_time":0.4784848117},
{"learn":[0.5335078954],"iteration":642,"passed_time":0.8590749119,"remaining_time":0.4769669418},
{"learn":[0.533426462],"iteration":643,"passed_time":0.859791888,"remaining_time":0.4752886834},
{"learn":[0.5324462408],"iteration":644,"passed_time":0.8605510739,"remaining_time":0.4736366376},
{"learn":[0.5313155856],"iteration":645,"passed_time":0.8616422481,"remaining_time":0.4721692815},
{"learn":[0.5300061113],"iteration":646,"passed_time":0.8626230475,"remaining_time":0.4706428683},
{"learn":[0.5288468082],"iteration":647,"passed_time":0.8641055732,"remaining_time":0.4693906818},
{"learn":[0.5287590703],"iteration":648,"passed_time":0.8654092316,"remaining_time":0.4680410482},
{"learn":[0.5286733513],"iteration":649,"passed_time":0.866418338,"remaining_time":0.4665329512},
{"learn":[0.5285940902],"iteration":650,"passed_time":0.8672974629,"remaining_time":0.4649567044},
{"learn":[0.5275373936],"iteration":651,"passed_time":0.8694663361,"remaining_time":0.4640709892},
{"learn":[0.527455579],"iteration":652,"passed_time":0.8724695898,"remaining_time":0.4636247284},
{"learn":[0.5262903402],"iteration":653,"passed_time":0.8894661546,"remaining_time":0.4705738371},
{"learn":[0.5262324675],"iteration":654,"passed_time":0.896959446,"remaining_time":0.4724442884},
{"learn":[0.5255215392],"iteration":655,"passed_time":0.9007210452,"remaining_time":0.4723293286},
{"learn":[0.5246930415],"iteration":656,"passed_time":0.9031257986,"remaining_time":0.4714948994},
{"learn":[0.5235056573],"iteration":657,"passed_time":0.9045484493,"remaining_time":0.4701452426},
{"learn":[0.5218455361],"iteration":658,"passed_time":0.9066438955,"remaining_time":0.4691435028},
{"learn":[0.5210714865],"iteration":659,"passed_time":0.9087559819,"remaining_time":0.468147021},
{"learn":[0.5206265735],"iteration":660,"passed_time":0.9110912733,"remaining_time":0.4672616364},
{"learn":[0.5205458053],"iteration":661,"passed_time":0.912776414,"remaining_time":0.4660399214},
{"learn":[0.5197973586],"iteration":662,"passed_time":0.916374416,"remaining_time":0.4657891074},
{"learn":[0.5191206424],"iteration":663,"passed_time":0.9177679386,"remaining_time":0.4644126918},
{"learn":[0.5190421695],"iteration":664,"passed_time":0.9188000433,"remaining_time":0.4628541571},
{"learn":[0.5183066166],"iteration":665,"passed_time":0.9199589117,"remaining_time":0.4613607755},
{"learn":[0.5182358378],"iteration":666,"passed_time":0.921090042,"remaining_time":0.4598545487},
{"learn":[0.5177700008],"iteration":667,"passed_time":0.922587014,"remaining_time":0.4585312704},
{"learn":[0.5170939716],"iteration":668,"passed_time":0.9248059741,"remaining_time":0.4575646897},
{"learn":[0.5153695388],"iteration":669,"passed_time":0.9257779026,"remaining_time":0.455980161},
{"learn":[0.5149341292],"iteration":670,"passed_time":0.927223701,"remaining_time":0.4546298027},
{"learn":[0.5139404256],"iteration":671,"passed_time":0.9287482106,"remaining_time":0.453317579},
{"learn":[0.513179703],"iteration":672,"passed_time":0.9303771068,"remaining_time":0.4520554442},
{"learn":[0.5115967303],"iteration":673,"passed_time":0.9313462626,"remaining_time":0.4504731181},
{"learn":[0.510773942],"iteration":674,"passed_time":0.9323215849,"remaining_time":0.4488955779},
{"learn":[0.5097790737],"iteration":675,"passed_time":0.9333527363,"remaining_time":0.4473465777},
{"learn":[0.5096373792],"iteration":676,"passed_time":0.9346975996,"remaining_time":0.4459487809},
{"learn":[0.5091665145],"iteration":677,"passed_time":0.9359820969,"remaining_time":0.4445224708},
{"learn":[0.5083347721],"iteration":678,"passed_time":0.9368553792,"remaining_time":0.4429021748},
{"learn":[0.5076632403],"iteration":679,"passed_time":0.9377184118,"remaining_time":0.4412792526},
{"learn":[0.507072558],"iteration":680,"passed_time":0.9388167341,"remaining_time":0.4397687785},
{"learn":[0.505936562],"iteration":681,"passed_time":0.9405967862,"remaining_time":0.4385773871},
{"learn":[0.5045130368],"iteration":682,"passed_time":0.941820695,"remaining_time":0.4371261498},
{"learn":[0.5038210871],"iteration":683,"passed_time":0.9426699702,"remaining_time":0.4355025009},
{"learn":[0.5032506587],"iteration":684,"passed_time":0.9434981399,"remaining_time":0.4338714074},
{"learn":[0.5022525753],"iteration":685,"passed_time":0.9461433317,"remaining_time":0.433074353},
{"learn":[0.5014860593],"iteration":686,"passed_time":0.9475911889,"remaining_time":0.4317264078},
{"learn":[0.5012396704],"iteration":687,"passed_time":0.9495922211,"remaining_time":0.4306290305},
{"learn":[0.5008518816],"iteration":688,"passed_time":0.9513554836,"remaining_time":0.429421706},
{"learn":[0.5002432013],"iteration":689,"passed_time":0.9532197695,"remaining_time":0.4282581573},
{"learn":[0.4992379014],"iteration":690,"passed_time":0.9575002101,"remaining_time":0.4281730317},
{"learn":[0.4986634194],"iteration":691,"passed_time":0.9636098937,"remaining_time":0.4288899527},
{"learn":[0.4984492819],"iteration":692,"passed_time":0.9652100606,"remaining_time":0.4275894497},
{"learn":[0.4978246382],"iteration":693,"passed_time":0.9665415727,"remaining_time":0.4261696272},
{"learn":[0.4971660037],"iteration":694,"passed_time":0.9690385136,"remaining_time":0.425261506},
{"learn":[0.4963299448],"iteration":695,"passed_time":0.9706991545,"remaining_time":0.4239835387},
{"learn":[0.4962559429],"iteration":696,"passed_time":0.9725604404,"remaining_time":0.4227916979},
{"learn":[0.4952246047],"iteration":697,"passed_time":0.9736226798,"remaining_time":0.4212522196},
{"learn":[0.4945771676],"iteration":698,"passed_time":0.9745523212,"remaining_time":0.4196570081},
{"learn":[0.4943775397],"iteration":699,"passed_time":0.975725132,"remaining_time":0.4181679137},
{"learn":[0.4934011242],"iteration":700,"passed_time":0.9768899708,"remaining_time":0.4166763214},
{"learn":[0.4933274058],"iteration":701,"passed_time":0.9783199546,"remaining_time":0.4152982144},
{"learn":[0.4923426768],"iteration":702,"passed_time":0.9799360673,"remaining_time":0.4139985946},
{"learn":[0.4921480211],"iteration":703,"passed_time":0.9811434949,"remaining_time":0.4125262422},
{"learn":[0.491612345],"iteration":704,"passed_time":0.9827594937,"remaining_time":0.4112256037},
{"learn":[0.4915429016],"iteration":705,"passed_time":0.9841750523,"remaining_time":0.4098406025},
{"learn":[0.4907213831],"iteration":706,"passed_time":0.9856784825,"remaining_time":0.4084919312},
{"learn":[0.4895476158],"iteration":707,"passed_time":0.9867624485,"remaining_time":0.4069698234},
{"learn":[0.489351525],"iteration":708,"passed_time":0.98762671,"remaining_time":0.4053587766},
{"learn":[0.489284435],"iteration":709,"passed_time":0.9886100121,"remaining_time":0.4037984556},
{"learn":[0.4880827988],"iteration":710,"passed_time":0.989685295,"remaining_time":0.4022771452},
{"learn":[0.4878444436],"iteration":711,"passed_time":0.9909673862,"remaining_time":0.4008407405},
{"learn":[0.4874651979],"iteration":712,"passed_time":0.9921066507,"remaining_time":0.3993472774},
{"learn":[0.4873970444],"iteration":713,"passed_time":0.9945738135,"remaining_time":0.3983867096},
{"learn":[0.4871401157],"iteration":714,"passed_time":0.9963331256,"remaining_time":0.3971397773},
{"learn":[0.4864559279],"iteration":715,"passed_time":0.9981534843,"remaining_time":0.3959156279},
{"learn":[0.4856330021],"iteration":716,"passed_time":0.9993920856,"remaining_time":0.3944601956},
{"learn":[0.4846645665],"iteration":717,"passed_time":1.000320262,"remaining_time":0.3928834455},
{"learn":[0.4844078368],"iteration":718,"passed_time":1.001285725,"remaining_time":0.3913230718},
{"learn":[0.4837830931],"iteration":719,"passed_time":1.002216624,"remaining_time":0.3897509092},
{"learn":[0.4831000068],"iteration":720,"passed_time":1.003373703,"remaining_time":0.3882680486},
{"learn":[0.4828125125],"iteration":721,"passed_time":1.004934981,"remaining_time":0.3869417239},
{"learn":[0.4827065298],"iteration":722,"passed_time":1.007664094,"remaining_time":0.3860621771},
{"learn":[0.4821489167],"iteration":723,"passed_time":1.008763379,"remaining_time":0.3845562053},
{"learn":[0.48086367],"iteration":724,"passed_time":1.010455649,"remaining_time":0.3832762807},
{"learn":[0.4798003513],"iteration":725,"passed_time":1.012286549,"remaining_time":0.3820475407},
{"learn":[0.479569867],"iteration":726,"passed_time":1.0136378,"remaining_time":0.380637028},
{"learn":[0.4786498584],"iteration":727,"passed_time":1.014544546,"remaining_time":0.3790605995},
{"learn":[0.4780375953],"iteration":728,"passed_time":1.015529425,"remaining_time":0.3775150537},
{"learn":[0.4775388043],"iteration":729,"passed_time":1.016494196,"remaining_time":0.3759636067},
{"learn":[0.4771101034],"iteration":730,"passed_time":1.01775712,"remaining_time":0.3745234818},
{"learn":[0.476588589],"iteration":731,"passed_time":1.019358263,"remaining_time":0.37320767},
{"learn":[0.4755431368],"iteration":732,"passed_time":1.021662148,"remaining_time":0.3721470581},
{"learn":[0.4749480088],"iteration":733,"passed_time":1.023151784,"remaining_time":0.3707879764},
{"learn":[0.4739504107],"iteration":734,"passed_time":1.024743932,"remaining_time":0.3694654992},
{"learn":[0.4730517401],"iteration":735,"passed_time":1.026430266,"remaining_time":0.3681760738},
{"learn":[0.4724933829],"iteration":736,"passed_time":1.027487425,"remaining_time":0.3666610484},
{"learn":[0.4718080628],"iteration":737,"passed_time":1.028449472,"remaining_time":0.3651134981},
{"learn":[0.471244374],"iteration":738,"passed_time":1.029415457,"remaining_time":0.3635689231},
{"learn":[0.4707228173],"iteration":739,"passed_time":1.030455265,"remaining_time":0.3620518498},
{"learn":[0.4704096871],"iteration":740,"passed_time":1.031595967,"remaining_time":0.36057133},
{"learn":[0.4701041848],"iteration":741,"passed_time":1.033138409,"remaining_time":0.3592314145},
{"learn":[0.4689949531],"iteration":742,"passed_time":1.035910869,"remaining_time":0.358316411},
{"learn":[0.4678786878],"iteration":743,"passed_time":1.037755512,"remaining_time":0.3570771655},
{"learn":[0.4674856347],"iteration":744,"passed_time":1.039689889,"remaining_time":0.355867009},
{"learn":[0.4669653001],"iteration":745,"passed_time":1.041046923,"remaining_time":0.3544583355},
{"learn":[0.4668630906],"iteration":746,"passed_time":1.042054475,"remaining_time":0.3529314353},
{"learn":[0.4661180038],"iteration":747,"passed_time":1.042930568,"remaining_time":0.3513616354},
{"learn":[0.4659604253],"iteration":748,"passed_time":1.043753053,"remaining_time":0.3497757226},
{"learn":[0.465651375],"iteration":749,"passed_time":1.044648792,"remaining_time":0.3482162641},
{"learn":[0.4644993799],"iteration":750,"passed_time":1.045952809,"remaining_time":0.3467939408},
{"learn":[0.4634431214],"iteration":751,"passed_time":1.04694725,"remaining_time":0.3452698376},
{"learn":[0.4629512668],"iteration":752,"passed_time":1.048125209,"remaining_time":0.3438073393},
{"learn":[0.4614935934],"iteration":753,"passed_time":1.049806009,"remaining_time":0.342509653},
{"learn":[0.4607120166],"iteration":754,"passed_time":1.051116432,"remaining_time":0.3410907627},
{"learn":[0.4604850464],"iteration":755,"passed_time":1.052353948,"remaining_time":0.3396486287},
{"learn":[0.4600463084],"iteration":756,"passed_time":1.05401821,"remaining_time":0.3383440224},
{"learn":[0.4591213582],"iteration":757,"passed_time":1.055367158,"remaining_time":0.3369377998},
{"learn":[0.458110585],"iteration":758,"passed_time":1.056686411,"remaining_time":0.3355222993},
{"learn":[0.457204908],"iteration":759,"passed_time":1.057552407,"remaining_time":0.3339639179},
{"learn":[0.4566646866],"iteration":760,"passed_time":1.058410313,"remaining_time":0.3324048159},
{"learn":[0.4561265059],"iteration":761,"passed_time":1.059396449,"remaining_time":0.3308876047},
{"learn":[0.4558461597],"iteration":762,"passed_time":1.060814181,"remaining_time":0.3295058466},
{"learn":[0.454809488],"iteration":763,"passed_time":1.062125951,"remaining_time":0.3280912624},
{"learn":[0.4545992202],"iteration":764,"passed_time":1.063927409,"remaining_time":0.3268273739},
{"learn":[0.4542619099],"iteration":765,"passed_time":1.06506931,"remaining_time":0.3253605987},
{"learn":[0.4537078747],"iteration":766,"passed_time":1.067283679,"remaining_time":0.3242204657},
{"learn":[0.4527879063],"iteration":767,"passed_time":1.069285787,"remaining_time":0.3230134147},
{"learn":[0.4524738069],"iteration":768,"passed_time":1.070369142,"remaining_time":0.3215283119},
{"learn":[0.4521981445],"iteration":769,"passed_time":1.071267456,"remaining_time":0.3199889805},
{"learn":[0.451068882],"iteration":770,"passed_time":1.072225006,"remaining_time":0.3184689058},
{"learn":[0.4510167153],"iteration":771,"passed_time":1.073084579,"remaining_time":0.3169213524},
{"learn":[0.4504103178],"iteration":772,"passed_time":1.074435673,"remaining_time":0.3155199195},
{"learn":[0.4498071585],"iteration":773,"passed_time":1.075690063,"remaining_time":0.3140903802},
{"learn":[0.4481564978],"iteration":774,"passed_time":1.077546631,"remaining_time":0.3128361187},
{"learn":[0.4479122654],"iteration":775,"passed_time":1.079007042,"remaining_time":0.3114659502},
{"learn":[0.4474342184],"iteration":776,"passed_time":1.080120764,"remaining_time":0.3099960493},
{"learn":[0.4465604744],"iteration":777,"passed_time":1.081580973,"remaining_time":0.3086259331},
{"learn":[0.4457649719],"iteration":778,"passed_time":1.083339298,"remaining_time":0.3073401602},
{"learn":[0.4455310112],"iteration":779,"passed_time":1.08489613,"remaining_time":0.3059963444},
{"learn":[0.4450492022],"iteration":780,"passed_time":1.08612875,"remaining_time":0.3045610707},
{"learn":[0.4437548668],"iteration":781,"passed_time":1.087145002,"remaining_time":0.3030659979},
{"learn":[0.4435531963],"iteration":782,"passed_time":1.08825283,"remaining_time":0.3015975276},
{"learn":[0.4429458599],"iteration":783,"passed_time":1.089586979,"remaining_time":0.300192331},
{"learn":[0.4425378023],"iteration":784,"passed_time":1.091120025,"remaining_time":0.2988417903},
{"learn":[0.4424475545],"iteration":785,"passed_time":1.092243867,"remaining_time":0.2973793735},
{"learn":[0.4419017367],"iteration":786,"passed_time":1.093959074,"remaining_time":0.2960778688},
{"learn":[0.4411225512],"iteration":787,"passed_time":1.095472748,"remaining_time":0.2947210945},
{"learn":[0.4407008509],"iteration":788,"passed_time":1.096960744,"remaining_time":0.2933570558},
{"learn":[0.4402205147],"iteration":789,"passed_time":1.098342684,"remaining_time":0.2919645111},
{"learn":[0.4394738089],"iteration":790,"passed_time":1.099351009,"remaining_time":0.2904732754},
{"learn":[0.438807395],"iteration":791,"passed_time":1.100232603,"remaining_time":0.2889499765},
{"learn":[0.4382763963],"iteration":792,"passed_time":1.10120511,"remaining_time":0.2874520276},
{"learn":[0.4378452083],"iteration":793,"passed_time":1.102457891,"remaining_time":0.2860281177},
{"learn":[0.4373302016],"iteration":794,"passed_time":1.103406822,"remaining_time":0.2845262875},
{"learn":[0.4361472608],"iteration":795,"passed_time":1.104437936,"remaining_time":0.2830469081},
{"learn":[0.4355572369],"iteration":796,"passed_time":1.10550961,"remaining_time":0.2815789848},
{"learn":[0.4345954954],"iteration":797,"passed_time":1.106568791,"remaining_time":0.2801088919},
{"learn":[0.4337828869],"iteration":798,"passed_time":1.108282364,"remaining_time":0.2788044494},
{"learn":[0.4331064684],"iteration":799,"passed_time":1.110452967,"remaining_time":0.2776132417},
{"learn":[0.4322298125],"iteration":800,"passed_time":1.111676792,"remaining_time":0.2761843716},
{"learn":[0.4317690639],"iteration":801,"passed_time":1.113459746,"remaining_time":0.274894052},
{"learn":[0.4305978981],"iteration":802,"passed_time":1.11497076,"remaining_time":0.2735357904},
{"learn":[0.4301151152],"iteration":803,"passed_time":1.116423902,"remaining_time":0.2721630408},
{"learn":[0.4286242928],"iteration":804,"passed_time":1.117703363,"remaining_time":0.2707480195},
{"learn":[0.4273187977],"iteration":805,"passed_time":1.118888804,"remaining_time":0.2693107047},
{"learn":[0.4272611718],"iteration":806,"passed_time":1.120538404,"remaining_time":0.267985021},
{"learn":[0.426370503],"iteration":807,"passed_time":1.122379031,"remaining_time":0.2667039282},
{"learn":[0.4256457943],"iteration":808,"passed_time":1.124276527,"remaining_time":0.2654348784},
{"learn":[0.4246386554],"iteration":809,"passed_time":1.125958014,"remaining_time":0.2641136082},
{"learn":[0.423978505],"iteration":810,"passed_time":1.127364185,"remaining_time":0.2627272885},
{"learn":[0.423511808],"iteration":811,"passed_time":1.128300675,"remaining_time":0.261232176},
{"learn":[0.4225335698],"iteration":812,"passed_time":1.12924588,"remaining_time":0.2597404422},
{"learn":[0.4220503459],"iteration":813,"passed_time":1.130353006,"remaining_time":0.2582870506},
{"learn":[0.4210023548],"iteration":814,"passed_time":1.131368925,"remaining_time":0.2568138051},
{"learn":[0.4200594235],"iteration":815,"passed_time":1.132378032,"remaining_time":0.2553401444},
{"learn":[0.4196288058],"iteration":816,"passed_time":1.133808217,"remaining_time":0.2539619384},
{"learn":[0.4189197557],"iteration":817,"passed_time":1.135187928,"remaining_time":0.2525723752},
{"learn":[0.4182310814],"iteration":818,"passed_time":1.136893425,"remaining_time":0.2512548352},
{"learn":[0.4176777535],"iteration":819,"passed_time":1.138427367,"remaining_time":0.2498986903},
{"learn":[0.4171505495],"iteration":820,"passed_time":1.139603158,"remaining_time":0.2484640259},
{"learn":[0.4165446916],"iteration":821,"passed_time":1.140693821,"remaining_time":0.2470115573},
{"learn":[0.4155746828],"iteration":822,"passed_time":1.14163562,"remaining_time":0.2455279523},
{"learn":[0.4151258029],"iteration":823,"passed_time":1.142662312,"remaining_time":0.2440637948},
{"learn":[0.4150707305],"iteration":824,"passed_time":1.143535228,"remaining_time":0.2425680786},
{"learn":[0.4146784549],"iteration":825,"passed_time":1.144413722,"remaining_time":0.2410750456},
{"learn":[0.413649704],"iteration":826,"passed_time":1.145324715,"remaining_time":0.2395902971},
{"learn":[0.4132380622],"iteration":827,"passed_time":1.146300845,"remaining_time":0.2381204654},
{"learn":[0.4123933208],"iteration":828,"passed_time":1.147801926,"remaining_time":0.2367601078},
{"learn":[0.4122471311],"iteration":829,"passed_time":1.148799418,"remaining_time":0.2352962663},
{"learn":[0.4112159099],"iteration":830,"passed_time":1.149733353,"remaining_time":0.2338206217},
{"learn":[0.4104977119],"iteration":831,"passed_time":1.150626296,"remaining_time":0.232338002},
{"learn":[0.4101811409],"iteration":832,"passed_time":1.152027909,"remaining_time":0.2309587764},
{"learn":[0.4098016366],"iteration":833,"passed_time":1.15332931,"remaining_time":0.229559551},
{"learn":[0.409749419],"iteration":834,"passed_time":1.154443618,"remaining_time":0.2281235893},
{"learn":[0.4088879526],"iteration":835,"passed_time":1.155314031,"remaining_time":0.2266405516},
{"learn":[0.4079577535],"iteration":836,"passed_time":1.156291771,"remaining_time":0.2251798789},
{"learn":[0.4072505514],"iteration":837,"passed_time":1.157413296,"remaining_time":0.2237481552},
{"learn":[0.4067768619],"iteration":838,"passed_time":1.158342836,"remaining_time":0.2222803297},
{"learn":[0.4060423612],"iteration":839,"passed_time":1.159190465,"remaining_time":0.2207981839},
{"learn":[0.4052976431],"iteration":840,"passed_time":1.160061403,"remaining_time":0.2193219537},
{"learn":[0.4045621182],"iteration":841,"passed_time":1.160933116,"remaining_time":0.2178473067},
{"learn":[0.4037155539],"iteration":842,"passed_time":1.16223666,"remaining_time":0.2164545144},
{"learn":[0.4035316116],"iteration":843,"passed_time":1.163426049,"remaining_time":0.2150408336},
{"learn":[0.4032931571],"iteration":844,"passed_time":1.164422823,"remaining_time":0.2135923522},
{"learn":[0.402706547],"iteration":845,"passed_time":1.165960587,"remaining_time":0.2122434165},
{"learn":[0.40225587],"iteration":846,"passed_time":1.167485925,"remaining_time":0.2108917904},
{"learn":[0.4017604176],"iteration":847,"passed_time":1.169081954,"remaining_time":0.2095524256},
{"learn":[0.4010608086],"iteration":848,"passed_time":1.170200232,"remaining_time":0.2081274853},
{"learn":[0.4006982792],"iteration":849,"passed_time":1.171118512,"remaining_time":0.2066679727},
{"learn":[0.3999982769],"iteration":850,"passed_time":1.171980208,"remaining_time":0.2051998249},
{"learn":[0.3991151726],"iteration":851,"passed_time":1.172816347,"remaining_time":0.2037286613},
{"learn":[0.3983575608],"iteration":852,"passed_time":1.173781558,"remaining_time":0.2022812299},
{"learn":[0.39767705],"iteration":853,"passed_time":1.174665188,"remaining_time":0.2008209805},
{"learn":[0.3968391217],"iteration":854,"passed_time":1.17566477,"remaining_time":0.1993817446},
{"learn":[0.3962682808],"iteration":855,"passed_time":1.176862202,"remaining_time":0.1979768191},
{"learn":[0.3952607874],"iteration":856,"passed_time":1.177849726,"remaining_time":0.1965373521},
{"learn":[0.3945062572],"iteration":857,"passed_time":1.179509332,"remaining_time":0.1952101691},
{"learn":[0.3940265896],"iteration":858,"passed_time":1.181077515,"remaining_time":0.1938672055},
{"learn":[0.3930977297],"iteration":859,"passed_time":1.182445131,"remaining_time":0.1924910678},
{"learn":[0.3927006551],"iteration":860,"passed_time":1.183435689,"remaining_time":0.1910540776},
{"learn":[0.392039018],"iteration":861,"passed_time":1.18431719,"remaining_time":0.1896006639},
{"learn":[0.3913179858],"iteration":862,"passed_time":1.185168911,"remaining_time":0.188143848},
{"learn":[0.3907808049],"iteration":863,"passed_time":1.18596846,"remaining_time":0.1866802205},
{"learn":[0.3906171574],"iteration":864,"passed_time":1.186770383,"remaining_time":0.1852184991},
{"learn":[0.3901371086],"iteration":865,"passed_time":1.18754817,"remaining_time":0.1837545668},
{"learn":[0.3891874821],"iteration":866,"passed_time":1.188371664,"remaining_time":0.1822992288},
{"learn":[0.3889130958],"iteration":867,"passed_time":1.189291093,"remaining_time":0.1808599358},
{"learn":[0.388262567],"iteration":868,"passed_time":1.190482235,"remaining_time":0.1794627995},
{"learn":[0.3874530581],"iteration":869,"passed_time":1.191544158,"remaining_time":0.1780468282},
{"learn":[0.3869608147],"iteration":870,"passed_time":1.193318523,"remaining_time":0.1767371865},
{"learn":[0.3867628494],"iteration":871,"passed_time":1.195042194,"remaining_time":0.1754190377},
{"learn":[0.3857925559],"iteration":872,"passed_time":1.196397846,"remaining_time":0.174046422},
{"learn":[0.3856191542],"iteration":873,"passed_time":1.197315711,"remaining_time":0.1726107317},
{"learn":[0.3847147863],"iteration":874,"passed_time":1.198164978,"remaining_time":0.1711664254},
{"learn":[0.3839741399],"iteration":875,"passed_time":1.199054189,"remaining_time":0.1697291317},
{"learn":[0.3836100249],"iteration":876,"passed_time":1.199861246,"remaining_time":0.1682815658},
{"learn":[0.3831078596],"iteration":877,"passed_time":1.200722304,"remaining_time":0.1668429626},
{"learn":[0.38276203],"iteration":878,"passed_time":1.201548591,"remaining_time":0.1654008869},
{"learn":[0.3826267482],"iteration":879,"passed_time":1.202329563,"remaining_time":0.1639540314},
{"learn":[0.3819128906],"iteration":880,"passed_time":1.203253452,"remaining_time":0.1625279918},
{"learn":[0.3814655516],"iteration":881,"passed_time":1.20413683,"remaining_time":0.1610976711},
{"learn":[0.3808088096],"iteration":882,"passed_time":1.207208238,"remaining_time":0.1599585094},
{"learn":[0.380143032],"iteration":883,"passed_time":1.208518893,"remaining_time":0.1585839271},
{"learn":[0.3796328487],"iteration":884,"passed_time":1.209717158,"remaining_time":0.157194885},
{"learn":[0.3791339636],"iteration":885,"passed_time":1.210643969,"remaining_time":0.1557713458},
{"learn":[0.3786460969],"iteration":886,"passed_time":1.211722924,"remaining_time":0.1543683094},
{"learn":[0.378303623],"iteration":887,"passed_time":1.212612493,"remaining_time":0.1529421162},
{"learn":[0.3780299916],"iteration":888,"passed_time":1.213423842,"remaining_time":0.1515073639},
{"learn":[0.3776639565],"iteration":889,"passed_time":1.214183844,"remaining_time":0.1500676661},
{"learn":[0.3769445809],"iteration":890,"passed_time":1.215026227,"remaining_time":0.1486395722},
{"learn":[0.3759977784],"iteration":891,"passed_time":1.215821034,"remaining_time":0.147207031},
{"learn":[0.375633119],"iteration":892,"passed_time":1.216604637,"remaining_time":0.1457745758},
{"learn":[0.3754451672],"iteration":893,"passed_time":1.217553111,"remaining_time":0.1443631206},
{"learn":[0.3750840336],"iteration":894,"passed_time":1.218329275,"remaining_time":0.1429324847},
{"learn":[0.3739735376],"iteration":895,"passed_time":1.219330992,"remaining_time":0.1415294902},
{"learn":[0.3738630224],"iteration":896,"passed_time":1.220236721,"remaining_time":0.1401163682},
{"learn":[0.372997232],"iteration":897,"passed_time":1.221641026,"remaining_time":0.1387610074},
{"learn":[0.3728412994],"iteration":898,"passed_time":1.223051114,"remaining_time":0.1374061874},
{"learn":[0.3718535885],"iteration":899,"passed_time":1.224776286,"remaining_time":0.136086254},
{"learn":[0.3713144992],"iteration":900,"passed_time":1.225681706,"remaining_time":0.1346753484},
{"learn":[0.3709842486],"iteration":901,"passed_time":1.226471593,"remaining_time":0.1332530113},
{"learn":[0.3703967954],"iteration":902,"passed_time":1.227318337,"remaining_time":0.1318381824},
{"learn":[0.3702418048],"iteration":903,"passed_time":1.228122674,"remaining_time":0.130420107},
{"learn":[0.3697831731],"iteration":904,"passed_time":1.229006061,"remaining_time":0.129011686},
{"learn":[0.3692612054],"iteration":905,"passed_time":1.233443439,"remaining_time":0.1279731603},
{"learn":[0.3687095931],"iteration":906,"passed_time":1.235522631,"remaining_time":0.1266853415},
{"learn":[0.3683379756],"iteration":907,"passed_time":1.23679225,"remaining_time":0.1253137522},
{"learn":[0.3681897903],"iteration":908,"passed_time":1.238851761,"remaining_time":0.1240214634},
{"learn":[0.3679210777],"iteration":909,"passed_time":1.24063531,"remaining_time":0.1227001955},
{"learn":[0.3670775925],"iteration":910,"passed_time":1.244271826,"remaining_time":0.121558938},
{"learn":[0.3659983721],"iteration":911,"passed_time":1.247281189,"remaining_time":0.1203516937},
{"learn":[0.3652131131],"iteration":912,"passed_time":1.24872272,"remaining_time":0.1189911025},
{"learn":[0.3641035851],"iteration":913,"passed_time":1.249800267,"remaining_time":0.1175960864},
{"learn":[0.3637029554],"iteration":914,"passed_time":1.250968283,"remaining_time":0.1162101684},
{"learn":[0.3627478814],"iteration":915,"passed_time":1.252095102,"remaining_time":0.1148209482},
{"learn":[0.3622852943],"iteration":916,"passed_time":1.253357769,"remaining_time":0.1134445964},
{"learn":[0.3619184698],"iteration":917,"passed_time":1.254498886,"remaining_time":0.1120576347},
{"learn":[0.3611413154],"iteration":918,"passed_time":1.255661544,"remaining_time":0.1106731067},
{"learn":[0.3607920793],"iteration":919,"passed_time":1.257140226,"remaining_time":0.1093165414},
{"learn":[0.3605362252],"iteration":920,"passed_time":1.259874536,"remaining_time":0.108067414},
{"learn":[0.3603324299],"iteration":921,"passed_time":1.262536178,"remaining_time":0.1068089175},
{"learn":[0.3596355687],"iteration":922,"passed_time":1.264375734,"remaining_time":0.105478799},
{"learn":[0.3591368236],"iteration":923,"passed_time":1.268077319,"remaining_time":0.1043007319},
{"learn":[0.3586029357],"iteration":924,"passed_time":1.273642372,"remaining_time":0.1032683005},
{"learn":[0.3577793061],"iteration":925,"passed_time":1.27929192,"remaining_time":0.1022328316},
{"learn":[0.3569030795],"iteration":926,"passed_time":1.28181421,"remaining_time":0.1009411406},
{"learn":[0.3563015769],"iteration":927,"passed_time":1.285338066,"remaining_time":0.09972450512},
{"learn":[0.3556665501],"iteration":928,"passed_time":1.286927087,"remaining_time":0.0983550303},
{"learn":[0.3552909991],"iteration":929,"passed_time":1.28798905,"remaining_time":0.09694541236},
{"learn":[0.3546664431],"iteration":930,"passed_time":1.289297806,"remaining_time":0.09555483202},
{"learn":[0.3543302527],"iteration":931,"passed_time":1.291119623,"remaining_time":0.0942018609},
{"learn":[0.3537592594],"iteration":932,"passed_time":1.292363285,"remaining_time":0.09280636663},
{"learn":[0.3525513982],"iteration":933,"passed_time":1.293472317,"remaining_time":0.09140168408},
{"learn":[0.3520942122],"iteration":934,"passed_time":1.294401989,"remaining_time":0.08998516498},
{"learn":[0.3519997301],"iteration":935,"passed_time":1.295380197,"remaining_time":0.08857300491},
{"learn":[0.3514654433],"iteration":936,"passed_time":1.296709575,"remaining_time":0.08718538228},
{"learn":[0.3505577682],"iteration":937,"passed_time":1.298244044,"remaining_time":0.08581144},
{"learn":[0.3497727663],"iteration":938,"passed_time":1.299713496,"remaining_time":0.08443293212},
{"learn":[0.349487658],"iteration":939,"passed_time":1.30085962,"remaining_time":0.08303359279},
{"learn":[0.3486606053],"iteration":940,"passed_time":1.302076544,"remaining_time":0.08163923074},
{"learn":[0.3479360468],"iteration":941,"passed_time":1.30364797,"remaining_time":0.08026707246},
{"learn":[0.3473365063],"iteration":942,"passed_time":1.305265653,"remaining_time":0.07889728762},
{"learn":[0.3464356364],"iteration":943,"passed_time":1.306340326,"remaining_time":0.07749476507},
{"learn":[0.345748063],"iteration":944,"passed_time":1.307392216,"remaining_time":0.07609161044},
{"learn":[0.3454834966],"iteration":945,"passed_time":1.308425575,"remaining_time":0.07468814063},
{"learn":[0.3452258067],"iteration":946,"passed_time":1.309315127,"remaining_time":0.07327740417},
{"learn":[0.3449887126],"iteration":947,"passed_time":1.310432198,"remaining_time":0.07188024717},
{"learn":[0.3445371484],"iteration":948,"passed_time":1.311302023,"remaining_time":0.07047039323},
{"learn":[0.3443138917],"iteration":949,"passed_time":1.312501959,"remaining_time":0.06907905046},
{"learn":[0.3441271588],"iteration":950,"passed_time":1.314539409,"remaining_time":0.06773126292},
{"learn":[0.3435857799],"iteration":951,"passed_time":1.315822852,"remaining_time":0.06634400935},
{"learn":[0.3434205822],"iteration":952,"passed_time":1.317460453,"remaining_time":0.06497443995},
{"learn":[0.3432639527],"iteration":953,"passed_time":1.318664893,"remaining_time":0.06358342252},
{"learn":[0.3424417562],"iteration":954,"passed_time":1.319802291,"remaining_time":0.06218963675},
{"learn":[0.3413578135],"iteration":955,"passed_time":1.320990422,"remaining_time":0.06079872235},
{"learn":[0.3409730116],"iteration":956,"passed_time":1.3219751,"remaining_time":0.05939909018},
{"learn":[0.3402530382],"iteration":957,"passed_time":1.322894073,"remaining_time":0.0579974437},
{"learn":[0.3400234231],"iteration":958,"passed_time":1.323766912,"remaining_time":0.05659483148},
{"learn":[0.3397726414],"iteration":959,"passed_time":1.324623351,"remaining_time":0.05519263964},
{"learn":[0.3393650095],"iteration":960,"passed_time":1.325630643,"remaining_time":0.05379770559},
{"learn":[0.3386975123],"iteration":961,"passed_time":1.326989075,"remaining_time":0.05241744788},
{"learn":[0.3378870485],"iteration":962,"passed_time":1.328685712,"remaining_time":0.05105022986},
{"learn":[0.3377068841],"iteration":963,"passed_time":1.329982331,"remaining_time":0.04966738997},
{"learn":[0.3375110111],"iteration":964,"passed_time":1.331268528,"remaining_time":0.04828435074},
{"learn":[0.3370503708],"iteration":965,"passed_time":1.332661052,"remaining_time":0.04690525441},
{"learn":[0.336603885],"iteration":966,"passed_time":1.333561535,"remaining_time":0.04550933884},
{"learn":[0.3356177951],"iteration":967,"passed_time":1.334394135,"remaining_time":0.04411220282},
{"learn":[0.3352014559],"iteration":968,"passed_time":1.335305588,"remaining_time":0.04271875461},
{"learn":[0.3350924923],"iteration":969,"passed_time":1.336117118,"remaining_time":0.04132320984},
{"learn":[0.334254969],"iteration":970,"passed_time":1.336973552,"remaining_time":0.03993020907},
{"learn":[0.3338856693],"iteration":971,"passed_time":1.337912536,"remaining_time":0.03854069034},
{"learn":[0.3337017694],"iteration":972,"passed_time":1.338782583,"remaining_time":0.03715018474},
{"learn":[0.333039386],"iteration":973,"passed_time":1.339595286,"remaining_time":0.03575921707},
{"learn":[0.3325834421],"iteration":974,"passed_time":1.34046342,"remaining_time":0.03437085693},
{"learn":[0.3322367537],"iteration":975,"passed_time":1.3418388,"remaining_time":0.03299603606},
{"learn":[0.3320509785],"iteration":976,"passed_time":1.343300363,"remaining_time":0.03162324293},
{"learn":[0.3315557926],"iteration":977,"passed_time":1.344427441,"remaining_time":0.03024274407},
{"learn":[0.3311061537],"iteration":978,"passed_time":1.345334829,"remaining_time":0.02885805048},
{"learn":[0.3306534784],"iteration":979,"passed_time":1.346243572,"remaining_time":0.02747435861},
{"learn":[0.329966227],"iteration":980,"passed_time":1.347634752,"remaining_time":0.02610097889},
{"learn":[0.3291885006],"iteration":981,"passed_time":1.348601586,"remaining_time":0.02471978468},
{"learn":[0.3288166596],"iteration":982,"passed_time":1.349416826,"remaining_time":0.02333681184},
{"learn":[0.328368101],"iteration":983,"passed_time":1.350271695,"remaining_time":0.02195563732},
{"learn":[0.3278811088],"iteration":984,"passed_time":1.351068382,"remaining_time":0.02057464541},
{"learn":[0.3267034339],"iteration":985,"passed_time":1.351857806,"remaining_time":0.01919473558},
{"learn":[0.3261504018],"iteration":986,"passed_time":1.352740614,"remaining_time":0.01781725226},
{"learn":[0.3258219856],"iteration":987,"passed_time":1.353689204,"remaining_time":0.01644156928},
{"learn":[0.3253266875],"iteration":988,"passed_time":1.354542689,"remaining_time":0.01506569219},
{"learn":[0.3251959394],"iteration":989,"passed_time":1.355554847,"remaining_time":0.0136924732},
{"learn":[0.3251532918],"iteration":990,"passed_time":1.356322707,"remaining_time":0.01231776424},
{"learn":[0.3245157774],"iteration":991,"passed_time":1.357213493,"remaining_time":0.0109452701},
{"learn":[0.3240922472],"iteration":992,"passed_time":1.358127639,"remaining_time":0.00957391085},
{"learn":[0.3238170307],"iteration":993,"passed_time":1.359595006,"remaining_time":0.008206810901},
{"learn":[0.3232274027],"iteration":994,"passed_time":1.360792904,"remaining_time":0.006838155298},
{"learn":[0.3228038885],"iteration":995,"passed_time":1.362381035,"remaining_time":0.005471409779},
{"learn":[0.3225836228],"iteration":996,"passed_time":1.363788276,"remaining_time":0.004103675856},
{"learn":[0.3222045476],"iteration":997,"passed_time":1.364767097,"remaining_time":0.002735004203},
{"learn":[0.3218956765],"iteration":998,"passed_time":1.365752313,"remaining_time":0.001367119432},
{"learn":[0.3215186638],"iteration":999,"passed_time":1.366591943,"remaining_time":0}
]}